{"v":"5.5.7","fr":30,"ip":0,"op":90,"w":1053,"h":592,"nm":"Comp 1","ddd":0,"assets":[{"id":"comp_0","layers":[{"ddd":0,"ind":1,"ty":4,"nm":"Layer 20 Outlines 15","sr":1,"ks":{"o":{"a":0,"k":100,"ix":11},"r":{"a":0,"k":0,"ix":10},"p":{"a":0,"k":[1609.276,401.891,0],"ix":2},"a":{"a":0,"k":[42.149,45.882,0],"ix":1},"s":{"a":0,"k":[100,100,100],"ix":6}},"ao":0,"shapes":[{"ty":"gr","it":[{"ind":0,"ty":"sh","ix":1,"ks":{"a":0,"k":{"i":[[0,-9.518],[9.518,0],[0,9.518],[-9.518,0]],"o":[[0,9.518],[-9.518,0],[0,-9.518],[9.518,0]],"v":[[17.235,0],[0.001,17.234],[-17.235,0],[0.001,-17.234]],"c":true},"ix":2},"nm":"Path 1","mn":"ADBE Vector Shape - Group","hd":false},{"ty":"mm","mm":4,"nm":"Merge Paths 1","mn":"ADBE Vector Filter - Merge","hd":false},{"ty":"fl","c":{"a":0,"k":[0.16470588235294117,0.2627450980392157,0.4627450980392157,1],"ix":4},"o":{"a":0,"k":100,"ix":5},"r":1,"bm":0,"nm":"Fill 1","mn":"ADBE Vector Graphic - Fill","hd":false},{"ty":"tr","p":{"a":0,"k":[41.054,30.915],"ix":2},"a":{"a":0,"k":[0,0],"ix":1},"s":{"a":1,"k":[{"i":{"x":[0.204,0.204],"y":[1,1]},"o":{"x":[0.333,0.333],"y":[0,0]},"t":138,"s":[0,0]},{"t":145.000005905971,"s":[100,100]}],"ix":3},"r":{"a":0,"k":0,"ix":6},"o":{"a":0,"k":100,"ix":7},"sk":{"a":0,"k":0,"ix":4},"sa":{"a":0,"k":0,"ix":5},"nm":"Transform"}],"nm":"Group 1","np":3,"cix":2,"bm":0,"ix":1,"mn":"ADBE Vector Group","hd":false},{"ty":"gr","it":[{"ind":0,"ty":"sh","ix":1,"ks":{"a":1,"k":[{"i":{"x":0.833,"y":1},"o":{"x":0.167,"y":0},"t":138,"s":[{"i":[[0,0],[14.573,0],[10.873,2.507],[0,0],[0,0]],"o":[[-13.801,2.007],[-13.395,0],[0,0],[0,0],[0,0]],"v":[[37.15,15.273],[-1.595,17.258],[-37.149,13.648],[-37.15,18.055],[37.15,18.055]],"c":true}]},{"i":{"x":0,"y":1},"o":{"x":0.333,"y":0},"t":140,"s":[{"i":[[0,0],[14.573,0],[9.134,-8.411],[0,0],[0,0]],"o":[[-9.335,-9.76],[-13.395,0],[0,0],[0,0],[0,0]],"v":[[37.15,15.273],[-0.595,10.195],[-37.149,13.648],[-37.15,18.055],[37.15,18.055]],"c":true}]},{"t":146.000005946702,"s":[{"i":[[0,0],[14.573,0],[9.134,-8.411],[0,0],[0,0]],"o":[[-9.335,-9.76],[-13.395,0],[0,0],[0,0],[0,0]],"v":[[37.15,-2.227],[-1.096,-18.055],[-37.15,-3.852],[-37.15,18.055],[37.15,18.055]],"c":true}]}],"ix":2},"nm":"Path 1","mn":"ADBE Vector Shape - Group","hd":false},{"ty":"mm","mm":4,"nm":"Merge Paths 1","mn":"ADBE Vector Filter - Merge","hd":false},{"ty":"fl","c":{"a":0,"k":[0.16470588235294117,0.2627450980392157,0.4627450980392157,1],"ix":4},"o":{"a":0,"k":100,"ix":5},"r":1,"bm":0,"nm":"Fill 1","mn":"ADBE Vector Graphic - Fill","hd":false},{"ty":"tr","p":{"a":0,"k":[42.149,68.71],"ix":2},"a":{"a":0,"k":[0,0],"ix":1},"s":{"a":0,"k":[100,100],"ix":3},"r":{"a":0,"k":0,"ix":6},"o":{"a":1,"k":[{"i":{"x":[0.833],"y":[0.833]},"o":{"x":[0.167],"y":[0.167]},"t":138,"s":[0]},{"t":140.000005702317,"s":[100]}],"ix":7},"sk":{"a":0,"k":0,"ix":4},"sa":{"a":0,"k":0,"ix":5},"nm":"Transform"}],"nm":"Group 2","np":3,"cix":2,"bm":0,"ix":2,"mn":"ADBE Vector Group","hd":false},{"ty":"gr","it":[{"ind":0,"ty":"sh","ix":1,"ks":{"a":0,"k":{"i":[[1.567,0],[0,0],[0,1.566],[0,0],[-1.566,0],[0,0],[0,-1.567],[0,0]],"o":[[0,0],[-1.566,0],[0,0],[0,-1.567],[0,0],[1.567,0],[0,0],[0,1.566]],"v":[[34.313,40.882],[-34.312,40.882],[-37.149,38.046],[-37.149,-38.045],[-34.312,-40.882],[34.313,-40.882],[37.149,-38.045],[37.149,38.046]],"c":true},"ix":2},"nm":"Path 1","mn":"ADBE Vector Shape - Group","hd":false},{"ty":"tm","s":{"a":0,"k":0,"ix":1},"e":{"a":1,"k":[{"i":{"x":[0.024],"y":[1]},"o":{"x":[0.333],"y":[0]},"t":138,"s":[0]},{"t":145.000005905971,"s":[100]}],"ix":2},"o":{"a":0,"k":0,"ix":3},"m":1,"ix":2,"nm":"Trim Paths 1","mn":"ADBE Vector Filter - Trim","hd":false},{"ty":"st","c":{"a":0,"k":[0.16470588235294117,0.2627450980392157,0.4627450980392157,1],"ix":3},"o":{"a":0,"k":100,"ix":4},"w":{"a":0,"k":2,"ix":5},"lc":1,"lj":1,"ml":10,"bm":0,"nm":"Stroke 1","mn":"ADBE Vector Graphic - Stroke","hd":false},{"ty":"tr","p":{"a":0,"k":[42.149,45.883],"ix":2},"a":{"a":0,"k":[0,0],"ix":1},"s":{"a":0,"k":[100,100],"ix":3},"r":{"a":0,"k":0,"ix":6},"o":{"a":0,"k":100,"ix":7},"sk":{"a":0,"k":0,"ix":4},"sa":{"a":0,"k":0,"ix":5},"nm":"Transform"}],"nm":"Group 3","np":3,"cix":2,"bm":0,"ix":3,"mn":"ADBE Vector Group","hd":false}],"ip":138.000005620855,"op":4634.00018874669,"st":138.000005620855,"bm":0},{"ddd":0,"ind":2,"ty":4,"nm":"Layer 20 Outlines 14","sr":1,"ks":{"o":{"a":0,"k":100,"ix":11},"r":{"a":0,"k":0,"ix":10},"p":{"a":0,"k":[1511.276,401.891,0],"ix":2},"a":{"a":0,"k":[42.149,45.882,0],"ix":1},"s":{"a":0,"k":[100,100,100],"ix":6}},"ao":0,"shapes":[{"ty":"gr","it":[{"ind":0,"ty":"sh","ix":1,"ks":{"a":0,"k":{"i":[[0,-9.518],[9.518,0],[0,9.518],[-9.518,0]],"o":[[0,9.518],[-9.518,0],[0,-9.518],[9.518,0]],"v":[[17.235,0],[0.001,17.234],[-17.235,0],[0.001,-17.234]],"c":true},"ix":2},"nm":"Path 1","mn":"ADBE Vector Shape - Group","hd":false},{"ty":"mm","mm":4,"nm":"Merge Paths 1","mn":"ADBE Vector Filter - Merge","hd":false},{"ty":"fl","c":{"a":0,"k":[0.16470588235294117,0.2627450980392157,0.4627450980392157,1],"ix":4},"o":{"a":0,"k":100,"ix":5},"r":1,"bm":0,"nm":"Fill 1","mn":"ADBE Vector Graphic - Fill","hd":false},{"ty":"tr","p":{"a":0,"k":[41.054,30.915],"ix":2},"a":{"a":0,"k":[0,0],"ix":1},"s":{"a":1,"k":[{"i":{"x":[0.204,0.204],"y":[1,1]},"o":{"x":[0.333,0.333],"y":[0,0]},"t":131,"s":[0,0]},{"t":138.000005620855,"s":[100,100]}],"ix":3},"r":{"a":0,"k":0,"ix":6},"o":{"a":0,"k":100,"ix":7},"sk":{"a":0,"k":0,"ix":4},"sa":{"a":0,"k":0,"ix":5},"nm":"Transform"}],"nm":"Group 1","np":3,"cix":2,"bm":0,"ix":1,"mn":"ADBE Vector Group","hd":false},{"ty":"gr","it":[{"ind":0,"ty":"sh","ix":1,"ks":{"a":1,"k":[{"i":{"x":0.833,"y":1},"o":{"x":0.167,"y":0},"t":131,"s":[{"i":[[0,0],[14.573,0],[10.873,2.507],[0,0],[0,0]],"o":[[-13.801,2.007],[-13.395,0],[0,0],[0,0],[0,0]],"v":[[37.15,15.273],[-1.595,17.258],[-37.149,13.648],[-37.15,18.055],[37.15,18.055]],"c":true}]},{"i":{"x":0,"y":1},"o":{"x":0.333,"y":0},"t":133,"s":[{"i":[[0,0],[14.573,0],[9.134,-8.411],[0,0],[0,0]],"o":[[-9.335,-9.76],[-13.395,0],[0,0],[0,0],[0,0]],"v":[[37.15,15.273],[-0.595,10.195],[-37.149,13.648],[-37.15,18.055],[37.15,18.055]],"c":true}]},{"t":139.000005661586,"s":[{"i":[[0,0],[14.573,0],[9.134,-8.411],[0,0],[0,0]],"o":[[-9.335,-9.76],[-13.395,0],[0,0],[0,0],[0,0]],"v":[[37.15,-2.227],[-1.096,-18.055],[-37.15,-3.852],[-37.15,18.055],[37.15,18.055]],"c":true}]}],"ix":2},"nm":"Path 1","mn":"ADBE Vector Shape - Group","hd":false},{"ty":"mm","mm":4,"nm":"Merge Paths 1","mn":"ADBE Vector Filter - Merge","hd":false},{"ty":"fl","c":{"a":0,"k":[0.16470588235294117,0.2627450980392157,0.4627450980392157,1],"ix":4},"o":{"a":0,"k":100,"ix":5},"r":1,"bm":0,"nm":"Fill 1","mn":"ADBE Vector Graphic - Fill","hd":false},{"ty":"tr","p":{"a":0,"k":[42.149,68.71],"ix":2},"a":{"a":0,"k":[0,0],"ix":1},"s":{"a":0,"k":[100,100],"ix":3},"r":{"a":0,"k":0,"ix":6},"o":{"a":1,"k":[{"i":{"x":[0.833],"y":[0.833]},"o":{"x":[0.167],"y":[0.167]},"t":131,"s":[0]},{"t":133.000005417201,"s":[100]}],"ix":7},"sk":{"a":0,"k":0,"ix":4},"sa":{"a":0,"k":0,"ix":5},"nm":"Transform"}],"nm":"Group 2","np":3,"cix":2,"bm":0,"ix":2,"mn":"ADBE Vector Group","hd":false},{"ty":"gr","it":[{"ind":0,"ty":"sh","ix":1,"ks":{"a":0,"k":{"i":[[1.567,0],[0,0],[0,1.566],[0,0],[-1.566,0],[0,0],[0,-1.567],[0,0]],"o":[[0,0],[-1.566,0],[0,0],[0,-1.567],[0,0],[1.567,0],[0,0],[0,1.566]],"v":[[34.313,40.882],[-34.312,40.882],[-37.149,38.046],[-37.149,-38.045],[-34.312,-40.882],[34.313,-40.882],[37.149,-38.045],[37.149,38.046]],"c":true},"ix":2},"nm":"Path 1","mn":"ADBE Vector Shape - Group","hd":false},{"ty":"tm","s":{"a":0,"k":0,"ix":1},"e":{"a":1,"k":[{"i":{"x":[0.024],"y":[1]},"o":{"x":[0.333],"y":[0]},"t":131,"s":[0]},{"t":138.000005620855,"s":[100]}],"ix":2},"o":{"a":0,"k":0,"ix":3},"m":1,"ix":2,"nm":"Trim Paths 1","mn":"ADBE Vector Filter - Trim","hd":false},{"ty":"st","c":{"a":0,"k":[0.16470588235294117,0.2627450980392157,0.4627450980392157,1],"ix":3},"o":{"a":0,"k":100,"ix":4},"w":{"a":0,"k":2,"ix":5},"lc":1,"lj":1,"ml":10,"bm":0,"nm":"Stroke 1","mn":"ADBE Vector Graphic - Stroke","hd":false},{"ty":"tr","p":{"a":0,"k":[42.149,45.883],"ix":2},"a":{"a":0,"k":[0,0],"ix":1},"s":{"a":0,"k":[100,100],"ix":3},"r":{"a":0,"k":0,"ix":6},"o":{"a":0,"k":100,"ix":7},"sk":{"a":0,"k":0,"ix":4},"sa":{"a":0,"k":0,"ix":5},"nm":"Transform"}],"nm":"Group 3","np":3,"cix":2,"bm":0,"ix":3,"mn":"ADBE Vector Group","hd":false}],"ip":131.000005335739,"op":4627.00018846157,"st":131.000005335739,"bm":0},{"ddd":0,"ind":3,"ty":4,"nm":"Layer 20 Outlines 13","sr":1,"ks":{"o":{"a":0,"k":100,"ix":11},"r":{"a":0,"k":0,"ix":10},"p":{"a":0,"k":[1411.276,401.891,0],"ix":2},"a":{"a":0,"k":[42.149,45.882,0],"ix":1},"s":{"a":0,"k":[100,100,100],"ix":6}},"ao":0,"shapes":[{"ty":"gr","it":[{"ind":0,"ty":"sh","ix":1,"ks":{"a":0,"k":{"i":[[0,-9.518],[9.518,0],[0,9.518],[-9.518,0]],"o":[[0,9.518],[-9.518,0],[0,-9.518],[9.518,0]],"v":[[17.235,0],[0.001,17.234],[-17.235,0],[0.001,-17.234]],"c":true},"ix":2},"nm":"Path 1","mn":"ADBE Vector Shape - Group","hd":false},{"ty":"mm","mm":4,"nm":"Merge Paths 1","mn":"ADBE Vector Filter - Merge","hd":false},{"ty":"fl","c":{"a":0,"k":[0.16470588235294117,0.2627450980392157,0.4627450980392157,1],"ix":4},"o":{"a":0,"k":100,"ix":5},"r":1,"bm":0,"nm":"Fill 1","mn":"ADBE Vector Graphic - Fill","hd":false},{"ty":"tr","p":{"a":0,"k":[41.054,30.915],"ix":2},"a":{"a":0,"k":[0,0],"ix":1},"s":{"a":1,"k":[{"i":{"x":[0.204,0.204],"y":[1,1]},"o":{"x":[0.333,0.333],"y":[0,0]},"t":124,"s":[0,0]},{"t":131.000005335739,"s":[100,100]}],"ix":3},"r":{"a":0,"k":0,"ix":6},"o":{"a":0,"k":100,"ix":7},"sk":{"a":0,"k":0,"ix":4},"sa":{"a":0,"k":0,"ix":5},"nm":"Transform"}],"nm":"Group 1","np":3,"cix":2,"bm":0,"ix":1,"mn":"ADBE Vector Group","hd":false},{"ty":"gr","it":[{"ind":0,"ty":"sh","ix":1,"ks":{"a":1,"k":[{"i":{"x":0.833,"y":1},"o":{"x":0.167,"y":0},"t":124,"s":[{"i":[[0,0],[14.573,0],[10.873,2.507],[0,0],[0,0]],"o":[[-13.801,2.007],[-13.395,0],[0,0],[0,0],[0,0]],"v":[[37.15,15.273],[-1.595,17.258],[-37.149,13.648],[-37.15,18.055],[37.15,18.055]],"c":true}]},{"i":{"x":0,"y":1},"o":{"x":0.333,"y":0},"t":126,"s":[{"i":[[0,0],[14.573,0],[9.134,-8.411],[0,0],[0,0]],"o":[[-9.335,-9.76],[-13.395,0],[0,0],[0,0],[0,0]],"v":[[37.15,15.273],[-0.595,10.195],[-37.149,13.648],[-37.15,18.055],[37.15,18.055]],"c":true}]},{"t":132.00000537647,"s":[{"i":[[0,0],[14.573,0],[9.134,-8.411],[0,0],[0,0]],"o":[[-9.335,-9.76],[-13.395,0],[0,0],[0,0],[0,0]],"v":[[37.15,-2.227],[-1.096,-18.055],[-37.15,-3.852],[-37.15,18.055],[37.15,18.055]],"c":true}]}],"ix":2},"nm":"Path 1","mn":"ADBE Vector Shape - Group","hd":false},{"ty":"mm","mm":4,"nm":"Merge Paths 1","mn":"ADBE Vector Filter - Merge","hd":false},{"ty":"fl","c":{"a":0,"k":[0.16470588235294117,0.2627450980392157,0.4627450980392157,1],"ix":4},"o":{"a":0,"k":100,"ix":5},"r":1,"bm":0,"nm":"Fill 1","mn":"ADBE Vector Graphic - Fill","hd":false},{"ty":"tr","p":{"a":0,"k":[42.149,68.71],"ix":2},"a":{"a":0,"k":[0,0],"ix":1},"s":{"a":0,"k":[100,100],"ix":3},"r":{"a":0,"k":0,"ix":6},"o":{"a":1,"k":[{"i":{"x":[0.833],"y":[0.833]},"o":{"x":[0.167],"y":[0.167]},"t":124,"s":[0]},{"t":126.000005132085,"s":[100]}],"ix":7},"sk":{"a":0,"k":0,"ix":4},"sa":{"a":0,"k":0,"ix":5},"nm":"Transform"}],"nm":"Group 2","np":3,"cix":2,"bm":0,"ix":2,"mn":"ADBE Vector Group","hd":false},{"ty":"gr","it":[{"ind":0,"ty":"sh","ix":1,"ks":{"a":0,"k":{"i":[[1.567,0],[0,0],[0,1.566],[0,0],[-1.566,0],[0,0],[0,-1.567],[0,0]],"o":[[0,0],[-1.566,0],[0,0],[0,-1.567],[0,0],[1.567,0],[0,0],[0,1.566]],"v":[[34.313,40.882],[-34.312,40.882],[-37.149,38.046],[-37.149,-38.045],[-34.312,-40.882],[34.313,-40.882],[37.149,-38.045],[37.149,38.046]],"c":true},"ix":2},"nm":"Path 1","mn":"ADBE Vector Shape - Group","hd":false},{"ty":"tm","s":{"a":0,"k":0,"ix":1},"e":{"a":1,"k":[{"i":{"x":[0.024],"y":[1]},"o":{"x":[0.333],"y":[0]},"t":124,"s":[0]},{"t":131.000005335739,"s":[100]}],"ix":2},"o":{"a":0,"k":0,"ix":3},"m":1,"ix":2,"nm":"Trim Paths 1","mn":"ADBE Vector Filter - Trim","hd":false},{"ty":"st","c":{"a":0,"k":[0.16470588235294117,0.2627450980392157,0.4627450980392157,1],"ix":3},"o":{"a":0,"k":100,"ix":4},"w":{"a":0,"k":2,"ix":5},"lc":1,"lj":1,"ml":10,"bm":0,"nm":"Stroke 1","mn":"ADBE Vector Graphic - Stroke","hd":false},{"ty":"tr","p":{"a":0,"k":[42.149,45.883],"ix":2},"a":{"a":0,"k":[0,0],"ix":1},"s":{"a":0,"k":[100,100],"ix":3},"r":{"a":0,"k":0,"ix":6},"o":{"a":0,"k":100,"ix":7},"sk":{"a":0,"k":0,"ix":4},"sa":{"a":0,"k":0,"ix":5},"nm":"Transform"}],"nm":"Group 3","np":3,"cix":2,"bm":0,"ix":3,"mn":"ADBE Vector Group","hd":false}],"ip":124.000005050624,"op":4620.00018817646,"st":124.000005050624,"bm":0},{"ddd":0,"ind":4,"ty":4,"nm":"Layer 20 Outlines 12","sr":1,"ks":{"o":{"a":0,"k":100,"ix":11},"r":{"a":0,"k":0,"ix":10},"p":{"a":0,"k":[1313.276,401.891,0],"ix":2},"a":{"a":0,"k":[42.149,45.882,0],"ix":1},"s":{"a":0,"k":[100,100,100],"ix":6}},"ao":0,"shapes":[{"ty":"gr","it":[{"ind":0,"ty":"sh","ix":1,"ks":{"a":0,"k":{"i":[[0,-9.518],[9.518,0],[0,9.518],[-9.518,0]],"o":[[0,9.518],[-9.518,0],[0,-9.518],[9.518,0]],"v":[[17.235,0],[0.001,17.234],[-17.235,0],[0.001,-17.234]],"c":true},"ix":2},"nm":"Path 1","mn":"ADBE Vector Shape - Group","hd":false},{"ty":"mm","mm":4,"nm":"Merge Paths 1","mn":"ADBE Vector Filter - Merge","hd":false},{"ty":"fl","c":{"a":0,"k":[0.16470588235294117,0.2627450980392157,0.4627450980392157,1],"ix":4},"o":{"a":0,"k":100,"ix":5},"r":1,"bm":0,"nm":"Fill 1","mn":"ADBE Vector Graphic - Fill","hd":false},{"ty":"tr","p":{"a":0,"k":[41.054,30.915],"ix":2},"a":{"a":0,"k":[0,0],"ix":1},"s":{"a":1,"k":[{"i":{"x":[0.204,0.204],"y":[1,1]},"o":{"x":[0.333,0.333],"y":[0,0]},"t":114,"s":[0,0]},{"t":121.000004928431,"s":[100,100]}],"ix":3},"r":{"a":0,"k":0,"ix":6},"o":{"a":0,"k":100,"ix":7},"sk":{"a":0,"k":0,"ix":4},"sa":{"a":0,"k":0,"ix":5},"nm":"Transform"}],"nm":"Group 1","np":3,"cix":2,"bm":0,"ix":1,"mn":"ADBE Vector Group","hd":false},{"ty":"gr","it":[{"ind":0,"ty":"sh","ix":1,"ks":{"a":1,"k":[{"i":{"x":0.833,"y":1},"o":{"x":0.167,"y":0},"t":114,"s":[{"i":[[0,0],[14.573,0],[10.873,2.507],[0,0],[0,0]],"o":[[-13.801,2.007],[-13.395,0],[0,0],[0,0],[0,0]],"v":[[37.15,15.273],[-1.595,17.258],[-37.149,13.648],[-37.15,18.055],[37.15,18.055]],"c":true}]},{"i":{"x":0,"y":1},"o":{"x":0.333,"y":0},"t":116,"s":[{"i":[[0,0],[14.573,0],[9.134,-8.411],[0,0],[0,0]],"o":[[-9.335,-9.76],[-13.395,0],[0,0],[0,0],[0,0]],"v":[[37.15,15.273],[-0.595,10.195],[-37.149,13.648],[-37.15,18.055],[37.15,18.055]],"c":true}]},{"t":122.000004969162,"s":[{"i":[[0,0],[14.573,0],[9.134,-8.411],[0,0],[0,0]],"o":[[-9.335,-9.76],[-13.395,0],[0,0],[0,0],[0,0]],"v":[[37.15,-2.227],[-1.096,-18.055],[-37.15,-3.852],[-37.15,18.055],[37.15,18.055]],"c":true}]}],"ix":2},"nm":"Path 1","mn":"ADBE Vector Shape - Group","hd":false},{"ty":"mm","mm":4,"nm":"Merge Paths 1","mn":"ADBE Vector Filter - Merge","hd":false},{"ty":"fl","c":{"a":0,"k":[0.16470588235294117,0.2627450980392157,0.4627450980392157,1],"ix":4},"o":{"a":0,"k":100,"ix":5},"r":1,"bm":0,"nm":"Fill 1","mn":"ADBE Vector Graphic - Fill","hd":false},{"ty":"tr","p":{"a":0,"k":[42.149,68.71],"ix":2},"a":{"a":0,"k":[0,0],"ix":1},"s":{"a":0,"k":[100,100],"ix":3},"r":{"a":0,"k":0,"ix":6},"o":{"a":1,"k":[{"i":{"x":[0.833],"y":[0.833]},"o":{"x":[0.167],"y":[0.167]},"t":114,"s":[0]},{"t":116.000004724777,"s":[100]}],"ix":7},"sk":{"a":0,"k":0,"ix":4},"sa":{"a":0,"k":0,"ix":5},"nm":"Transform"}],"nm":"Group 2","np":3,"cix":2,"bm":0,"ix":2,"mn":"ADBE Vector Group","hd":false},{"ty":"gr","it":[{"ind":0,"ty":"sh","ix":1,"ks":{"a":0,"k":{"i":[[1.567,0],[0,0],[0,1.566],[0,0],[-1.566,0],[0,0],[0,-1.567],[0,0]],"o":[[0,0],[-1.566,0],[0,0],[0,-1.567],[0,0],[1.567,0],[0,0],[0,1.566]],"v":[[34.313,40.882],[-34.312,40.882],[-37.149,38.046],[-37.149,-38.045],[-34.312,-40.882],[34.313,-40.882],[37.149,-38.045],[37.149,38.046]],"c":true},"ix":2},"nm":"Path 1","mn":"ADBE Vector Shape - Group","hd":false},{"ty":"tm","s":{"a":0,"k":0,"ix":1},"e":{"a":1,"k":[{"i":{"x":[0.024],"y":[1]},"o":{"x":[0.333],"y":[0]},"t":114,"s":[0]},{"t":121.000004928431,"s":[100]}],"ix":2},"o":{"a":0,"k":0,"ix":3},"m":1,"ix":2,"nm":"Trim Paths 1","mn":"ADBE Vector Filter - Trim","hd":false},{"ty":"st","c":{"a":0,"k":[0.16470588235294117,0.2627450980392157,0.4627450980392157,1],"ix":3},"o":{"a":0,"k":100,"ix":4},"w":{"a":0,"k":2,"ix":5},"lc":1,"lj":1,"ml":10,"bm":0,"nm":"Stroke 1","mn":"ADBE Vector Graphic - Stroke","hd":false},{"ty":"tr","p":{"a":0,"k":[42.149,45.883],"ix":2},"a":{"a":0,"k":[0,0],"ix":1},"s":{"a":0,"k":[100,100],"ix":3},"r":{"a":0,"k":0,"ix":6},"o":{"a":0,"k":100,"ix":7},"sk":{"a":0,"k":0,"ix":4},"sa":{"a":0,"k":0,"ix":5},"nm":"Transform"}],"nm":"Group 3","np":3,"cix":2,"bm":0,"ix":3,"mn":"ADBE Vector Group","hd":false}],"ip":114.000004643315,"op":4610.00018776915,"st":114.000004643315,"bm":0},{"ddd":0,"ind":5,"ty":4,"nm":"Layer 20 Outlines 11","sr":1,"ks":{"o":{"a":0,"k":100,"ix":11},"r":{"a":0,"k":0,"ix":10},"p":{"a":0,"k":[1213.276,401.891,0],"ix":2},"a":{"a":0,"k":[42.149,45.882,0],"ix":1},"s":{"a":0,"k":[100,100,100],"ix":6}},"ao":0,"shapes":[{"ty":"gr","it":[{"ind":0,"ty":"sh","ix":1,"ks":{"a":0,"k":{"i":[[0,-9.518],[9.518,0],[0,9.518],[-9.518,0]],"o":[[0,9.518],[-9.518,0],[0,-9.518],[9.518,0]],"v":[[17.235,0],[0.001,17.234],[-17.235,0],[0.001,-17.234]],"c":true},"ix":2},"nm":"Path 1","mn":"ADBE Vector Shape - Group","hd":false},{"ty":"mm","mm":4,"nm":"Merge Paths 1","mn":"ADBE Vector Filter - Merge","hd":false},{"ty":"fl","c":{"a":0,"k":[0.16470588235294117,0.2627450980392157,0.4627450980392157,1],"ix":4},"o":{"a":0,"k":100,"ix":5},"r":1,"bm":0,"nm":"Fill 1","mn":"ADBE Vector Graphic - Fill","hd":false},{"ty":"tr","p":{"a":0,"k":[41.054,30.915],"ix":2},"a":{"a":0,"k":[0,0],"ix":1},"s":{"a":1,"k":[{"i":{"x":[0.204,0.204],"y":[1,1]},"o":{"x":[0.333,0.333],"y":[0,0]},"t":107,"s":[0,0]},{"t":114.000004643315,"s":[100,100]}],"ix":3},"r":{"a":0,"k":0,"ix":6},"o":{"a":0,"k":100,"ix":7},"sk":{"a":0,"k":0,"ix":4},"sa":{"a":0,"k":0,"ix":5},"nm":"Transform"}],"nm":"Group 1","np":3,"cix":2,"bm":0,"ix":1,"mn":"ADBE Vector Group","hd":false},{"ty":"gr","it":[{"ind":0,"ty":"sh","ix":1,"ks":{"a":1,"k":[{"i":{"x":0.833,"y":1},"o":{"x":0.167,"y":0},"t":107,"s":[{"i":[[0,0],[14.573,0],[10.873,2.507],[0,0],[0,0]],"o":[[-13.801,2.007],[-13.395,0],[0,0],[0,0],[0,0]],"v":[[37.15,15.273],[-1.595,17.258],[-37.149,13.648],[-37.15,18.055],[37.15,18.055]],"c":true}]},{"i":{"x":0,"y":1},"o":{"x":0.333,"y":0},"t":109,"s":[{"i":[[0,0],[14.573,0],[9.134,-8.411],[0,0],[0,0]],"o":[[-9.335,-9.76],[-13.395,0],[0,0],[0,0],[0,0]],"v":[[37.15,15.273],[-0.595,10.195],[-37.149,13.648],[-37.15,18.055],[37.15,18.055]],"c":true}]},{"t":115.000004684046,"s":[{"i":[[0,0],[14.573,0],[9.134,-8.411],[0,0],[0,0]],"o":[[-9.335,-9.76],[-13.395,0],[0,0],[0,0],[0,0]],"v":[[37.15,-2.227],[-1.096,-18.055],[-37.15,-3.852],[-37.15,18.055],[37.15,18.055]],"c":true}]}],"ix":2},"nm":"Path 1","mn":"ADBE Vector Shape - Group","hd":false},{"ty":"mm","mm":4,"nm":"Merge Paths 1","mn":"ADBE Vector Filter - Merge","hd":false},{"ty":"fl","c":{"a":0,"k":[0.16470588235294117,0.2627450980392157,0.4627450980392157,1],"ix":4},"o":{"a":0,"k":100,"ix":5},"r":1,"bm":0,"nm":"Fill 1","mn":"ADBE Vector Graphic - Fill","hd":false},{"ty":"tr","p":{"a":0,"k":[42.149,68.71],"ix":2},"a":{"a":0,"k":[0,0],"ix":1},"s":{"a":0,"k":[100,100],"ix":3},"r":{"a":0,"k":0,"ix":6},"o":{"a":1,"k":[{"i":{"x":[0.833],"y":[0.833]},"o":{"x":[0.167],"y":[0.167]},"t":107,"s":[0]},{"t":109.000004439661,"s":[100]}],"ix":7},"sk":{"a":0,"k":0,"ix":4},"sa":{"a":0,"k":0,"ix":5},"nm":"Transform"}],"nm":"Group 2","np":3,"cix":2,"bm":0,"ix":2,"mn":"ADBE Vector Group","hd":false},{"ty":"gr","it":[{"ind":0,"ty":"sh","ix":1,"ks":{"a":0,"k":{"i":[[1.567,0],[0,0],[0,1.566],[0,0],[-1.566,0],[0,0],[0,-1.567],[0,0]],"o":[[0,0],[-1.566,0],[0,0],[0,-1.567],[0,0],[1.567,0],[0,0],[0,1.566]],"v":[[34.313,40.882],[-34.312,40.882],[-37.149,38.046],[-37.149,-38.045],[-34.312,-40.882],[34.313,-40.882],[37.149,-38.045],[37.149,38.046]],"c":true},"ix":2},"nm":"Path 1","mn":"ADBE Vector Shape - Group","hd":false},{"ty":"tm","s":{"a":0,"k":0,"ix":1},"e":{"a":1,"k":[{"i":{"x":[0.024],"y":[1]},"o":{"x":[0.333],"y":[0]},"t":107,"s":[0]},{"t":114.000004643315,"s":[100]}],"ix":2},"o":{"a":0,"k":0,"ix":3},"m":1,"ix":2,"nm":"Trim Paths 1","mn":"ADBE Vector Filter - Trim","hd":false},{"ty":"st","c":{"a":0,"k":[0.16470588235294117,0.2627450980392157,0.4627450980392157,1],"ix":3},"o":{"a":0,"k":100,"ix":4},"w":{"a":0,"k":2,"ix":5},"lc":1,"lj":1,"ml":10,"bm":0,"nm":"Stroke 1","mn":"ADBE Vector Graphic - Stroke","hd":false},{"ty":"tr","p":{"a":0,"k":[42.149,45.883],"ix":2},"a":{"a":0,"k":[0,0],"ix":1},"s":{"a":0,"k":[100,100],"ix":3},"r":{"a":0,"k":0,"ix":6},"o":{"a":0,"k":100,"ix":7},"sk":{"a":0,"k":0,"ix":4},"sa":{"a":0,"k":0,"ix":5},"nm":"Transform"}],"nm":"Group 3","np":3,"cix":2,"bm":0,"ix":3,"mn":"ADBE Vector Group","hd":false}],"ip":107.000004358199,"op":4603.00018748403,"st":107.000004358199,"bm":0},{"ddd":0,"ind":6,"ty":4,"nm":"Layer 20 Outlines 10","sr":1,"ks":{"o":{"a":0,"k":100,"ix":11},"r":{"a":0,"k":0,"ix":10},"p":{"a":0,"k":[1609.276,283.891,0],"ix":2},"a":{"a":0,"k":[42.149,45.882,0],"ix":1},"s":{"a":0,"k":[100,100,100],"ix":6}},"ao":0,"shapes":[{"ty":"gr","it":[{"ind":0,"ty":"sh","ix":1,"ks":{"a":0,"k":{"i":[[0,-9.518],[9.518,0],[0,9.518],[-9.518,0]],"o":[[0,9.518],[-9.518,0],[0,-9.518],[9.518,0]],"v":[[17.235,0],[0.001,17.234],[-17.235,0],[0.001,-17.234]],"c":true},"ix":2},"nm":"Path 1","mn":"ADBE Vector Shape - Group","hd":false},{"ty":"mm","mm":4,"nm":"Merge Paths 1","mn":"ADBE Vector Filter - Merge","hd":false},{"ty":"fl","c":{"a":0,"k":[0.16470588235294117,0.2627450980392157,0.4627450980392157,1],"ix":4},"o":{"a":0,"k":100,"ix":5},"r":1,"bm":0,"nm":"Fill 1","mn":"ADBE Vector Graphic - Fill","hd":false},{"ty":"tr","p":{"a":0,"k":[41.054,30.915],"ix":2},"a":{"a":0,"k":[0,0],"ix":1},"s":{"a":1,"k":[{"i":{"x":[0.204,0.204],"y":[1,1]},"o":{"x":[0.333,0.333],"y":[0,0]},"t":101,"s":[0,0]},{"t":108.00000439893,"s":[100,100]}],"ix":3},"r":{"a":0,"k":0,"ix":6},"o":{"a":0,"k":100,"ix":7},"sk":{"a":0,"k":0,"ix":4},"sa":{"a":0,"k":0,"ix":5},"nm":"Transform"}],"nm":"Group 1","np":3,"cix":2,"bm":0,"ix":1,"mn":"ADBE Vector Group","hd":false},{"ty":"gr","it":[{"ind":0,"ty":"sh","ix":1,"ks":{"a":1,"k":[{"i":{"x":0.833,"y":1},"o":{"x":0.167,"y":0},"t":101,"s":[{"i":[[0,0],[14.573,0],[10.873,2.507],[0,0],[0,0]],"o":[[-13.801,2.007],[-13.395,0],[0,0],[0,0],[0,0]],"v":[[37.15,15.273],[-1.595,17.258],[-37.149,13.648],[-37.15,18.055],[37.15,18.055]],"c":true}]},{"i":{"x":0,"y":1},"o":{"x":0.333,"y":0},"t":103,"s":[{"i":[[0,0],[14.573,0],[9.134,-8.411],[0,0],[0,0]],"o":[[-9.335,-9.76],[-13.395,0],[0,0],[0,0],[0,0]],"v":[[37.15,15.273],[-0.595,10.195],[-37.149,13.648],[-37.15,18.055],[37.15,18.055]],"c":true}]},{"t":109.000004439661,"s":[{"i":[[0,0],[14.573,0],[9.134,-8.411],[0,0],[0,0]],"o":[[-9.335,-9.76],[-13.395,0],[0,0],[0,0],[0,0]],"v":[[37.15,-2.227],[-1.096,-18.055],[-37.15,-3.852],[-37.15,18.055],[37.15,18.055]],"c":true}]}],"ix":2},"nm":"Path 1","mn":"ADBE Vector Shape - Group","hd":false},{"ty":"mm","mm":4,"nm":"Merge Paths 1","mn":"ADBE Vector Filter - Merge","hd":false},{"ty":"fl","c":{"a":0,"k":[0.16470588235294117,0.2627450980392157,0.4627450980392157,1],"ix":4},"o":{"a":0,"k":100,"ix":5},"r":1,"bm":0,"nm":"Fill 1","mn":"ADBE Vector Graphic - Fill","hd":false},{"ty":"tr","p":{"a":0,"k":[42.149,68.71],"ix":2},"a":{"a":0,"k":[0,0],"ix":1},"s":{"a":0,"k":[100,100],"ix":3},"r":{"a":0,"k":0,"ix":6},"o":{"a":1,"k":[{"i":{"x":[0.833],"y":[0.833]},"o":{"x":[0.167],"y":[0.167]},"t":101,"s":[0]},{"t":103.000004195276,"s":[100]}],"ix":7},"sk":{"a":0,"k":0,"ix":4},"sa":{"a":0,"k":0,"ix":5},"nm":"Transform"}],"nm":"Group 2","np":3,"cix":2,"bm":0,"ix":2,"mn":"ADBE Vector Group","hd":false},{"ty":"gr","it":[{"ind":0,"ty":"sh","ix":1,"ks":{"a":0,"k":{"i":[[1.567,0],[0,0],[0,1.566],[0,0],[-1.566,0],[0,0],[0,-1.567],[0,0]],"o":[[0,0],[-1.566,0],[0,0],[0,-1.567],[0,0],[1.567,0],[0,0],[0,1.566]],"v":[[34.313,40.882],[-34.312,40.882],[-37.149,38.046],[-37.149,-38.045],[-34.312,-40.882],[34.313,-40.882],[37.149,-38.045],[37.149,38.046]],"c":true},"ix":2},"nm":"Path 1","mn":"ADBE Vector Shape - Group","hd":false},{"ty":"tm","s":{"a":0,"k":0,"ix":1},"e":{"a":1,"k":[{"i":{"x":[0.024],"y":[1]},"o":{"x":[0.333],"y":[0]},"t":101,"s":[0]},{"t":108.00000439893,"s":[100]}],"ix":2},"o":{"a":0,"k":0,"ix":3},"m":1,"ix":2,"nm":"Trim Paths 1","mn":"ADBE Vector Filter - Trim","hd":false},{"ty":"st","c":{"a":0,"k":[0.16470588235294117,0.2627450980392157,0.4627450980392157,1],"ix":3},"o":{"a":0,"k":100,"ix":4},"w":{"a":0,"k":2,"ix":5},"lc":1,"lj":1,"ml":10,"bm":0,"nm":"Stroke 1","mn":"ADBE Vector Graphic - Stroke","hd":false},{"ty":"tr","p":{"a":0,"k":[42.149,45.883],"ix":2},"a":{"a":0,"k":[0,0],"ix":1},"s":{"a":0,"k":[100,100],"ix":3},"r":{"a":0,"k":0,"ix":6},"o":{"a":0,"k":100,"ix":7},"sk":{"a":0,"k":0,"ix":4},"sa":{"a":0,"k":0,"ix":5},"nm":"Transform"}],"nm":"Group 3","np":3,"cix":2,"bm":0,"ix":3,"mn":"ADBE Vector Group","hd":false}],"ip":101.000004113814,"op":4597.00018723965,"st":101.000004113814,"bm":0},{"ddd":0,"ind":7,"ty":4,"nm":"Layer 20 Outlines 9","sr":1,"ks":{"o":{"a":0,"k":100,"ix":11},"r":{"a":0,"k":0,"ix":10},"p":{"a":0,"k":[1511.276,283.891,0],"ix":2},"a":{"a":0,"k":[42.149,45.882,0],"ix":1},"s":{"a":0,"k":[100,100,100],"ix":6}},"ao":0,"shapes":[{"ty":"gr","it":[{"ind":0,"ty":"sh","ix":1,"ks":{"a":0,"k":{"i":[[0,-9.518],[9.518,0],[0,9.518],[-9.518,0]],"o":[[0,9.518],[-9.518,0],[0,-9.518],[9.518,0]],"v":[[17.235,0],[0.001,17.234],[-17.235,0],[0.001,-17.234]],"c":true},"ix":2},"nm":"Path 1","mn":"ADBE Vector Shape - Group","hd":false},{"ty":"mm","mm":4,"nm":"Merge Paths 1","mn":"ADBE Vector Filter - Merge","hd":false},{"ty":"fl","c":{"a":0,"k":[0.16470588235294117,0.2627450980392157,0.4627450980392157,1],"ix":4},"o":{"a":0,"k":100,"ix":5},"r":1,"bm":0,"nm":"Fill 1","mn":"ADBE Vector Graphic - Fill","hd":false},{"ty":"tr","p":{"a":0,"k":[41.054,30.915],"ix":2},"a":{"a":0,"k":[0,0],"ix":1},"s":{"a":1,"k":[{"i":{"x":[0.204,0.204],"y":[1,1]},"o":{"x":[0.333,0.333],"y":[0,0]},"t":94,"s":[0,0]},{"t":101.000004113814,"s":[100,100]}],"ix":3},"r":{"a":0,"k":0,"ix":6},"o":{"a":0,"k":100,"ix":7},"sk":{"a":0,"k":0,"ix":4},"sa":{"a":0,"k":0,"ix":5},"nm":"Transform"}],"nm":"Group 1","np":3,"cix":2,"bm":0,"ix":1,"mn":"ADBE Vector Group","hd":false},{"ty":"gr","it":[{"ind":0,"ty":"sh","ix":1,"ks":{"a":1,"k":[{"i":{"x":0.833,"y":1},"o":{"x":0.167,"y":0},"t":94,"s":[{"i":[[0,0],[14.573,0],[10.873,2.507],[0,0],[0,0]],"o":[[-13.801,2.007],[-13.395,0],[0,0],[0,0],[0,0]],"v":[[37.15,15.273],[-1.595,17.258],[-37.149,13.648],[-37.15,18.055],[37.15,18.055]],"c":true}]},{"i":{"x":0,"y":1},"o":{"x":0.333,"y":0},"t":96,"s":[{"i":[[0,0],[14.573,0],[9.134,-8.411],[0,0],[0,0]],"o":[[-9.335,-9.76],[-13.395,0],[0,0],[0,0],[0,0]],"v":[[37.15,15.273],[-0.595,10.195],[-37.149,13.648],[-37.15,18.055],[37.15,18.055]],"c":true}]},{"t":102.000004154545,"s":[{"i":[[0,0],[14.573,0],[9.134,-8.411],[0,0],[0,0]],"o":[[-9.335,-9.76],[-13.395,0],[0,0],[0,0],[0,0]],"v":[[37.15,-2.227],[-1.096,-18.055],[-37.15,-3.852],[-37.15,18.055],[37.15,18.055]],"c":true}]}],"ix":2},"nm":"Path 1","mn":"ADBE Vector Shape - Group","hd":false},{"ty":"mm","mm":4,"nm":"Merge Paths 1","mn":"ADBE Vector Filter - Merge","hd":false},{"ty":"fl","c":{"a":0,"k":[0.16470588235294117,0.2627450980392157,0.4627450980392157,1],"ix":4},"o":{"a":0,"k":100,"ix":5},"r":1,"bm":0,"nm":"Fill 1","mn":"ADBE Vector Graphic - Fill","hd":false},{"ty":"tr","p":{"a":0,"k":[42.149,68.71],"ix":2},"a":{"a":0,"k":[0,0],"ix":1},"s":{"a":0,"k":[100,100],"ix":3},"r":{"a":0,"k":0,"ix":6},"o":{"a":1,"k":[{"i":{"x":[0.833],"y":[0.833]},"o":{"x":[0.167],"y":[0.167]},"t":94,"s":[0]},{"t":96.0000039101602,"s":[100]}],"ix":7},"sk":{"a":0,"k":0,"ix":4},"sa":{"a":0,"k":0,"ix":5},"nm":"Transform"}],"nm":"Group 2","np":3,"cix":2,"bm":0,"ix":2,"mn":"ADBE Vector Group","hd":false},{"ty":"gr","it":[{"ind":0,"ty":"sh","ix":1,"ks":{"a":0,"k":{"i":[[1.567,0],[0,0],[0,1.566],[0,0],[-1.566,0],[0,0],[0,-1.567],[0,0]],"o":[[0,0],[-1.566,0],[0,0],[0,-1.567],[0,0],[1.567,0],[0,0],[0,1.566]],"v":[[34.313,40.882],[-34.312,40.882],[-37.149,38.046],[-37.149,-38.045],[-34.312,-40.882],[34.313,-40.882],[37.149,-38.045],[37.149,38.046]],"c":true},"ix":2},"nm":"Path 1","mn":"ADBE Vector Shape - Group","hd":false},{"ty":"tm","s":{"a":0,"k":0,"ix":1},"e":{"a":1,"k":[{"i":{"x":[0.024],"y":[1]},"o":{"x":[0.333],"y":[0]},"t":94,"s":[0]},{"t":101.000004113814,"s":[100]}],"ix":2},"o":{"a":0,"k":0,"ix":3},"m":1,"ix":2,"nm":"Trim Paths 1","mn":"ADBE Vector Filter - Trim","hd":false},{"ty":"st","c":{"a":0,"k":[0.16470588235294117,0.2627450980392157,0.4627450980392157,1],"ix":3},"o":{"a":0,"k":100,"ix":4},"w":{"a":0,"k":2,"ix":5},"lc":1,"lj":1,"ml":10,"bm":0,"nm":"Stroke 1","mn":"ADBE Vector Graphic - Stroke","hd":false},{"ty":"tr","p":{"a":0,"k":[42.149,45.883],"ix":2},"a":{"a":0,"k":[0,0],"ix":1},"s":{"a":0,"k":[100,100],"ix":3},"r":{"a":0,"k":0,"ix":6},"o":{"a":0,"k":100,"ix":7},"sk":{"a":0,"k":0,"ix":4},"sa":{"a":0,"k":0,"ix":5},"nm":"Transform"}],"nm":"Group 3","np":3,"cix":2,"bm":0,"ix":3,"mn":"ADBE Vector Group","hd":false}],"ip":94.0000038286985,"op":4590.00018695453,"st":94.0000038286985,"bm":0},{"ddd":0,"ind":8,"ty":4,"nm":"Layer 20 Outlines 8","sr":1,"ks":{"o":{"a":0,"k":100,"ix":11},"r":{"a":0,"k":0,"ix":10},"p":{"a":0,"k":[1411.276,283.891,0],"ix":2},"a":{"a":0,"k":[42.149,45.882,0],"ix":1},"s":{"a":0,"k":[100,100,100],"ix":6}},"ao":0,"shapes":[{"ty":"gr","it":[{"ind":0,"ty":"sh","ix":1,"ks":{"a":0,"k":{"i":[[0,-9.518],[9.518,0],[0,9.518],[-9.518,0]],"o":[[0,9.518],[-9.518,0],[0,-9.518],[9.518,0]],"v":[[17.235,0],[0.001,17.234],[-17.235,0],[0.001,-17.234]],"c":true},"ix":2},"nm":"Path 1","mn":"ADBE Vector Shape - Group","hd":false},{"ty":"mm","mm":4,"nm":"Merge Paths 1","mn":"ADBE Vector Filter - Merge","hd":false},{"ty":"fl","c":{"a":0,"k":[0.16470588235294117,0.2627450980392157,0.4627450980392157,1],"ix":4},"o":{"a":0,"k":100,"ix":5},"r":1,"bm":0,"nm":"Fill 1","mn":"ADBE Vector Graphic - Fill","hd":false},{"ty":"tr","p":{"a":0,"k":[41.054,30.915],"ix":2},"a":{"a":0,"k":[0,0],"ix":1},"s":{"a":1,"k":[{"i":{"x":[0.204,0.204],"y":[1,1]},"o":{"x":[0.333,0.333],"y":[0,0]},"t":87,"s":[0,0]},{"t":94.0000038286985,"s":[100,100]}],"ix":3},"r":{"a":0,"k":0,"ix":6},"o":{"a":0,"k":100,"ix":7},"sk":{"a":0,"k":0,"ix":4},"sa":{"a":0,"k":0,"ix":5},"nm":"Transform"}],"nm":"Group 1","np":3,"cix":2,"bm":0,"ix":1,"mn":"ADBE Vector Group","hd":false},{"ty":"gr","it":[{"ind":0,"ty":"sh","ix":1,"ks":{"a":1,"k":[{"i":{"x":0.833,"y":1},"o":{"x":0.167,"y":0},"t":87,"s":[{"i":[[0,0],[14.573,0],[10.873,2.507],[0,0],[0,0]],"o":[[-13.801,2.007],[-13.395,0],[0,0],[0,0],[0,0]],"v":[[37.15,15.273],[-1.595,17.258],[-37.149,13.648],[-37.15,18.055],[37.15,18.055]],"c":true}]},{"i":{"x":0,"y":1},"o":{"x":0.333,"y":0},"t":89,"s":[{"i":[[0,0],[14.573,0],[9.134,-8.411],[0,0],[0,0]],"o":[[-9.335,-9.76],[-13.395,0],[0,0],[0,0],[0,0]],"v":[[37.15,15.273],[-0.595,10.195],[-37.149,13.648],[-37.15,18.055],[37.15,18.055]],"c":true}]},{"t":95.0000038694293,"s":[{"i":[[0,0],[14.573,0],[9.134,-8.411],[0,0],[0,0]],"o":[[-9.335,-9.76],[-13.395,0],[0,0],[0,0],[0,0]],"v":[[37.15,-2.227],[-1.096,-18.055],[-37.15,-3.852],[-37.15,18.055],[37.15,18.055]],"c":true}]}],"ix":2},"nm":"Path 1","mn":"ADBE Vector Shape - Group","hd":false},{"ty":"mm","mm":4,"nm":"Merge Paths 1","mn":"ADBE Vector Filter - Merge","hd":false},{"ty":"fl","c":{"a":0,"k":[0.16470588235294117,0.2627450980392157,0.4627450980392157,1],"ix":4},"o":{"a":0,"k":100,"ix":5},"r":1,"bm":0,"nm":"Fill 1","mn":"ADBE Vector Graphic - Fill","hd":false},{"ty":"tr","p":{"a":0,"k":[42.149,68.71],"ix":2},"a":{"a":0,"k":[0,0],"ix":1},"s":{"a":0,"k":[100,100],"ix":3},"r":{"a":0,"k":0,"ix":6},"o":{"a":1,"k":[{"i":{"x":[0.833],"y":[0.833]},"o":{"x":[0.167],"y":[0.167]},"t":87,"s":[0]},{"t":89.0000036250443,"s":[100]}],"ix":7},"sk":{"a":0,"k":0,"ix":4},"sa":{"a":0,"k":0,"ix":5},"nm":"Transform"}],"nm":"Group 2","np":3,"cix":2,"bm":0,"ix":2,"mn":"ADBE Vector Group","hd":false},{"ty":"gr","it":[{"ind":0,"ty":"sh","ix":1,"ks":{"a":0,"k":{"i":[[1.567,0],[0,0],[0,1.566],[0,0],[-1.566,0],[0,0],[0,-1.567],[0,0]],"o":[[0,0],[-1.566,0],[0,0],[0,-1.567],[0,0],[1.567,0],[0,0],[0,1.566]],"v":[[34.313,40.882],[-34.312,40.882],[-37.149,38.046],[-37.149,-38.045],[-34.312,-40.882],[34.313,-40.882],[37.149,-38.045],[37.149,38.046]],"c":true},"ix":2},"nm":"Path 1","mn":"ADBE Vector Shape - Group","hd":false},{"ty":"tm","s":{"a":0,"k":0,"ix":1},"e":{"a":1,"k":[{"i":{"x":[0.024],"y":[1]},"o":{"x":[0.333],"y":[0]},"t":87,"s":[0]},{"t":94.0000038286985,"s":[100]}],"ix":2},"o":{"a":0,"k":0,"ix":3},"m":1,"ix":2,"nm":"Trim Paths 1","mn":"ADBE Vector Filter - Trim","hd":false},{"ty":"st","c":{"a":0,"k":[0.16470588235294117,0.2627450980392157,0.4627450980392157,1],"ix":3},"o":{"a":0,"k":100,"ix":4},"w":{"a":0,"k":2,"ix":5},"lc":1,"lj":1,"ml":10,"bm":0,"nm":"Stroke 1","mn":"ADBE Vector Graphic - Stroke","hd":false},{"ty":"tr","p":{"a":0,"k":[42.149,45.883],"ix":2},"a":{"a":0,"k":[0,0],"ix":1},"s":{"a":0,"k":[100,100],"ix":3},"r":{"a":0,"k":0,"ix":6},"o":{"a":0,"k":100,"ix":7},"sk":{"a":0,"k":0,"ix":4},"sa":{"a":0,"k":0,"ix":5},"nm":"Transform"}],"nm":"Group 3","np":3,"cix":2,"bm":0,"ix":3,"mn":"ADBE Vector Group","hd":false}],"ip":87.0000035435826,"op":4583.00018666942,"st":87.0000035435826,"bm":0},{"ddd":0,"ind":9,"ty":4,"nm":"Layer 20 Outlines 7","sr":1,"ks":{"o":{"a":0,"k":100,"ix":11},"r":{"a":0,"k":0,"ix":10},"p":{"a":0,"k":[1313.276,283.891,0],"ix":2},"a":{"a":0,"k":[42.149,45.882,0],"ix":1},"s":{"a":0,"k":[100,100,100],"ix":6}},"ao":0,"shapes":[{"ty":"gr","it":[{"ind":0,"ty":"sh","ix":1,"ks":{"a":0,"k":{"i":[[0,-9.518],[9.518,0],[0,9.518],[-9.518,0]],"o":[[0,9.518],[-9.518,0],[0,-9.518],[9.518,0]],"v":[[17.235,0],[0.001,17.234],[-17.235,0],[0.001,-17.234]],"c":true},"ix":2},"nm":"Path 1","mn":"ADBE Vector Shape - Group","hd":false},{"ty":"mm","mm":4,"nm":"Merge Paths 1","mn":"ADBE Vector Filter - Merge","hd":false},{"ty":"fl","c":{"a":0,"k":[0.16470588235294117,0.2627450980392157,0.4627450980392157,1],"ix":4},"o":{"a":0,"k":100,"ix":5},"r":1,"bm":0,"nm":"Fill 1","mn":"ADBE Vector Graphic - Fill","hd":false},{"ty":"tr","p":{"a":0,"k":[41.054,30.915],"ix":2},"a":{"a":0,"k":[0,0],"ix":1},"s":{"a":1,"k":[{"i":{"x":[0.204,0.204],"y":[1,1]},"o":{"x":[0.333,0.333],"y":[0,0]},"t":77,"s":[0,0]},{"t":84.0000034213901,"s":[100,100]}],"ix":3},"r":{"a":0,"k":0,"ix":6},"o":{"a":0,"k":100,"ix":7},"sk":{"a":0,"k":0,"ix":4},"sa":{"a":0,"k":0,"ix":5},"nm":"Transform"}],"nm":"Group 1","np":3,"cix":2,"bm":0,"ix":1,"mn":"ADBE Vector Group","hd":false},{"ty":"gr","it":[{"ind":0,"ty":"sh","ix":1,"ks":{"a":1,"k":[{"i":{"x":0.833,"y":1},"o":{"x":0.167,"y":0},"t":77,"s":[{"i":[[0,0],[14.573,0],[10.873,2.507],[0,0],[0,0]],"o":[[-13.801,2.007],[-13.395,0],[0,0],[0,0],[0,0]],"v":[[37.15,15.273],[-1.595,17.258],[-37.149,13.648],[-37.15,18.055],[37.15,18.055]],"c":true}]},{"i":{"x":0,"y":1},"o":{"x":0.333,"y":0},"t":79,"s":[{"i":[[0,0],[14.573,0],[9.134,-8.411],[0,0],[0,0]],"o":[[-9.335,-9.76],[-13.395,0],[0,0],[0,0],[0,0]],"v":[[37.15,15.273],[-0.595,10.195],[-37.149,13.648],[-37.15,18.055],[37.15,18.055]],"c":true}]},{"t":85.000003462121,"s":[{"i":[[0,0],[14.573,0],[9.134,-8.411],[0,0],[0,0]],"o":[[-9.335,-9.76],[-13.395,0],[0,0],[0,0],[0,0]],"v":[[37.15,-2.227],[-1.096,-18.055],[-37.15,-3.852],[-37.15,18.055],[37.15,18.055]],"c":true}]}],"ix":2},"nm":"Path 1","mn":"ADBE Vector Shape - Group","hd":false},{"ty":"mm","mm":4,"nm":"Merge Paths 1","mn":"ADBE Vector Filter - Merge","hd":false},{"ty":"fl","c":{"a":0,"k":[0.16470588235294117,0.2627450980392157,0.4627450980392157,1],"ix":4},"o":{"a":0,"k":100,"ix":5},"r":1,"bm":0,"nm":"Fill 1","mn":"ADBE Vector Graphic - Fill","hd":false},{"ty":"tr","p":{"a":0,"k":[42.149,68.71],"ix":2},"a":{"a":0,"k":[0,0],"ix":1},"s":{"a":0,"k":[100,100],"ix":3},"r":{"a":0,"k":0,"ix":6},"o":{"a":1,"k":[{"i":{"x":[0.833],"y":[0.833]},"o":{"x":[0.167],"y":[0.167]},"t":77,"s":[0]},{"t":79.000003217736,"s":[100]}],"ix":7},"sk":{"a":0,"k":0,"ix":4},"sa":{"a":0,"k":0,"ix":5},"nm":"Transform"}],"nm":"Group 2","np":3,"cix":2,"bm":0,"ix":2,"mn":"ADBE Vector Group","hd":false},{"ty":"gr","it":[{"ind":0,"ty":"sh","ix":1,"ks":{"a":0,"k":{"i":[[1.567,0],[0,0],[0,1.566],[0,0],[-1.566,0],[0,0],[0,-1.567],[0,0]],"o":[[0,0],[-1.566,0],[0,0],[0,-1.567],[0,0],[1.567,0],[0,0],[0,1.566]],"v":[[34.313,40.882],[-34.312,40.882],[-37.149,38.046],[-37.149,-38.045],[-34.312,-40.882],[34.313,-40.882],[37.149,-38.045],[37.149,38.046]],"c":true},"ix":2},"nm":"Path 1","mn":"ADBE Vector Shape - Group","hd":false},{"ty":"tm","s":{"a":0,"k":0,"ix":1},"e":{"a":1,"k":[{"i":{"x":[0.024],"y":[1]},"o":{"x":[0.333],"y":[0]},"t":77,"s":[0]},{"t":84.0000034213901,"s":[100]}],"ix":2},"o":{"a":0,"k":0,"ix":3},"m":1,"ix":2,"nm":"Trim Paths 1","mn":"ADBE Vector Filter - Trim","hd":false},{"ty":"st","c":{"a":0,"k":[0.16470588235294117,0.2627450980392157,0.4627450980392157,1],"ix":3},"o":{"a":0,"k":100,"ix":4},"w":{"a":0,"k":2,"ix":5},"lc":1,"lj":1,"ml":10,"bm":0,"nm":"Stroke 1","mn":"ADBE Vector Graphic - Stroke","hd":false},{"ty":"tr","p":{"a":0,"k":[42.149,45.883],"ix":2},"a":{"a":0,"k":[0,0],"ix":1},"s":{"a":0,"k":[100,100],"ix":3},"r":{"a":0,"k":0,"ix":6},"o":{"a":0,"k":100,"ix":7},"sk":{"a":0,"k":0,"ix":4},"sa":{"a":0,"k":0,"ix":5},"nm":"Transform"}],"nm":"Group 3","np":3,"cix":2,"bm":0,"ix":3,"mn":"ADBE Vector Group","hd":false}],"ip":77.0000031362743,"op":4573.00018626211,"st":77.0000031362743,"bm":0},{"ddd":0,"ind":10,"ty":4,"nm":"Layer 20 Outlines 6","sr":1,"ks":{"o":{"a":0,"k":100,"ix":11},"r":{"a":0,"k":0,"ix":10},"p":{"a":0,"k":[1213.276,283.891,0],"ix":2},"a":{"a":0,"k":[42.149,45.882,0],"ix":1},"s":{"a":0,"k":[100,100,100],"ix":6}},"ao":0,"shapes":[{"ty":"gr","it":[{"ind":0,"ty":"sh","ix":1,"ks":{"a":0,"k":{"i":[[0,-9.518],[9.518,0],[0,9.518],[-9.518,0]],"o":[[0,9.518],[-9.518,0],[0,-9.518],[9.518,0]],"v":[[17.235,0],[0.001,17.234],[-17.235,0],[0.001,-17.234]],"c":true},"ix":2},"nm":"Path 1","mn":"ADBE Vector Shape - Group","hd":false},{"ty":"mm","mm":4,"nm":"Merge Paths 1","mn":"ADBE Vector Filter - Merge","hd":false},{"ty":"fl","c":{"a":0,"k":[0.16470588235294117,0.2627450980392157,0.4627450980392157,1],"ix":4},"o":{"a":0,"k":100,"ix":5},"r":1,"bm":0,"nm":"Fill 1","mn":"ADBE Vector Graphic - Fill","hd":false},{"ty":"tr","p":{"a":0,"k":[41.054,30.915],"ix":2},"a":{"a":0,"k":[0,0],"ix":1},"s":{"a":1,"k":[{"i":{"x":[0.204,0.204],"y":[1,1]},"o":{"x":[0.333,0.333],"y":[0,0]},"t":70,"s":[0,0]},{"t":77.0000031362743,"s":[100,100]}],"ix":3},"r":{"a":0,"k":0,"ix":6},"o":{"a":0,"k":100,"ix":7},"sk":{"a":0,"k":0,"ix":4},"sa":{"a":0,"k":0,"ix":5},"nm":"Transform"}],"nm":"Group 1","np":3,"cix":2,"bm":0,"ix":1,"mn":"ADBE Vector Group","hd":false},{"ty":"gr","it":[{"ind":0,"ty":"sh","ix":1,"ks":{"a":1,"k":[{"i":{"x":0.833,"y":1},"o":{"x":0.167,"y":0},"t":70,"s":[{"i":[[0,0],[14.573,0],[10.873,2.507],[0,0],[0,0]],"o":[[-13.801,2.007],[-13.395,0],[0,0],[0,0],[0,0]],"v":[[37.15,15.273],[-1.595,17.258],[-37.149,13.648],[-37.15,18.055],[37.15,18.055]],"c":true}]},{"i":{"x":0,"y":1},"o":{"x":0.333,"y":0},"t":72,"s":[{"i":[[0,0],[14.573,0],[9.134,-8.411],[0,0],[0,0]],"o":[[-9.335,-9.76],[-13.395,0],[0,0],[0,0],[0,0]],"v":[[37.15,15.273],[-0.595,10.195],[-37.149,13.648],[-37.15,18.055],[37.15,18.055]],"c":true}]},{"t":78.0000031770051,"s":[{"i":[[0,0],[14.573,0],[9.134,-8.411],[0,0],[0,0]],"o":[[-9.335,-9.76],[-13.395,0],[0,0],[0,0],[0,0]],"v":[[37.15,-2.227],[-1.096,-18.055],[-37.15,-3.852],[-37.15,18.055],[37.15,18.055]],"c":true}]}],"ix":2},"nm":"Path 1","mn":"ADBE Vector Shape - Group","hd":false},{"ty":"mm","mm":4,"nm":"Merge Paths 1","mn":"ADBE Vector Filter - Merge","hd":false},{"ty":"fl","c":{"a":0,"k":[0.16470588235294117,0.2627450980392157,0.4627450980392157,1],"ix":4},"o":{"a":0,"k":100,"ix":5},"r":1,"bm":0,"nm":"Fill 1","mn":"ADBE Vector Graphic - Fill","hd":false},{"ty":"tr","p":{"a":0,"k":[42.149,68.71],"ix":2},"a":{"a":0,"k":[0,0],"ix":1},"s":{"a":0,"k":[100,100],"ix":3},"r":{"a":0,"k":0,"ix":6},"o":{"a":1,"k":[{"i":{"x":[0.833],"y":[0.833]},"o":{"x":[0.167],"y":[0.167]},"t":70,"s":[0]},{"t":72.0000029326201,"s":[100]}],"ix":7},"sk":{"a":0,"k":0,"ix":4},"sa":{"a":0,"k":0,"ix":5},"nm":"Transform"}],"nm":"Group 2","np":3,"cix":2,"bm":0,"ix":2,"mn":"ADBE Vector Group","hd":false},{"ty":"gr","it":[{"ind":0,"ty":"sh","ix":1,"ks":{"a":0,"k":{"i":[[1.567,0],[0,0],[0,1.566],[0,0],[-1.566,0],[0,0],[0,-1.567],[0,0]],"o":[[0,0],[-1.566,0],[0,0],[0,-1.567],[0,0],[1.567,0],[0,0],[0,1.566]],"v":[[34.313,40.882],[-34.312,40.882],[-37.149,38.046],[-37.149,-38.045],[-34.312,-40.882],[34.313,-40.882],[37.149,-38.045],[37.149,38.046]],"c":true},"ix":2},"nm":"Path 1","mn":"ADBE Vector Shape - Group","hd":false},{"ty":"tm","s":{"a":0,"k":0,"ix":1},"e":{"a":1,"k":[{"i":{"x":[0.024],"y":[1]},"o":{"x":[0.333],"y":[0]},"t":70,"s":[0]},{"t":77.0000031362743,"s":[100]}],"ix":2},"o":{"a":0,"k":0,"ix":3},"m":1,"ix":2,"nm":"Trim Paths 1","mn":"ADBE Vector Filter - Trim","hd":false},{"ty":"st","c":{"a":0,"k":[0.16470588235294117,0.2627450980392157,0.4627450980392157,1],"ix":3},"o":{"a":0,"k":100,"ix":4},"w":{"a":0,"k":2,"ix":5},"lc":1,"lj":1,"ml":10,"bm":0,"nm":"Stroke 1","mn":"ADBE Vector Graphic - Stroke","hd":false},{"ty":"tr","p":{"a":0,"k":[42.149,45.883],"ix":2},"a":{"a":0,"k":[0,0],"ix":1},"s":{"a":0,"k":[100,100],"ix":3},"r":{"a":0,"k":0,"ix":6},"o":{"a":0,"k":100,"ix":7},"sk":{"a":0,"k":0,"ix":4},"sa":{"a":0,"k":0,"ix":5},"nm":"Transform"}],"nm":"Group 3","np":3,"cix":2,"bm":0,"ix":3,"mn":"ADBE Vector Group","hd":false}],"ip":70.0000028511585,"op":4566.00018597699,"st":70.0000028511585,"bm":0},{"ddd":0,"ind":11,"ty":4,"nm":"Layer 20 Outlines 5","sr":1,"ks":{"o":{"a":0,"k":100,"ix":11},"r":{"a":0,"k":0,"ix":10},"p":{"a":0,"k":[1609.276,173.891,0],"ix":2},"a":{"a":0,"k":[42.149,45.882,0],"ix":1},"s":{"a":0,"k":[100,100,100],"ix":6}},"ao":0,"shapes":[{"ty":"gr","it":[{"ind":0,"ty":"sh","ix":1,"ks":{"a":0,"k":{"i":[[0,-9.518],[9.518,0],[0,9.518],[-9.518,0]],"o":[[0,9.518],[-9.518,0],[0,-9.518],[9.518,0]],"v":[[17.235,0],[0.001,17.234],[-17.235,0],[0.001,-17.234]],"c":true},"ix":2},"nm":"Path 1","mn":"ADBE Vector Shape - Group","hd":false},{"ty":"mm","mm":4,"nm":"Merge Paths 1","mn":"ADBE Vector Filter - Merge","hd":false},{"ty":"fl","c":{"a":0,"k":[0.16470588235294117,0.2627450980392157,0.4627450980392157,1],"ix":4},"o":{"a":0,"k":100,"ix":5},"r":1,"bm":0,"nm":"Fill 1","mn":"ADBE Vector Graphic - Fill","hd":false},{"ty":"tr","p":{"a":0,"k":[41.054,30.915],"ix":2},"a":{"a":0,"k":[0,0],"ix":1},"s":{"a":1,"k":[{"i":{"x":[0.204,0.204],"y":[1,1]},"o":{"x":[0.333,0.333],"y":[0,0]},"t":64,"s":[0,0]},{"t":71.0000028918893,"s":[100,100]}],"ix":3},"r":{"a":0,"k":0,"ix":6},"o":{"a":0,"k":100,"ix":7},"sk":{"a":0,"k":0,"ix":4},"sa":{"a":0,"k":0,"ix":5},"nm":"Transform"}],"nm":"Group 1","np":3,"cix":2,"bm":0,"ix":1,"mn":"ADBE Vector Group","hd":false},{"ty":"gr","it":[{"ind":0,"ty":"sh","ix":1,"ks":{"a":1,"k":[{"i":{"x":0.833,"y":1},"o":{"x":0.167,"y":0},"t":64,"s":[{"i":[[0,0],[14.573,0],[10.873,2.507],[0,0],[0,0]],"o":[[-13.801,2.007],[-13.395,0],[0,0],[0,0],[0,0]],"v":[[37.15,15.273],[-1.595,17.258],[-37.149,13.648],[-37.15,18.055],[37.15,18.055]],"c":true}]},{"i":{"x":0,"y":1},"o":{"x":0.333,"y":0},"t":66,"s":[{"i":[[0,0],[14.573,0],[9.134,-8.411],[0,0],[0,0]],"o":[[-9.335,-9.76],[-13.395,0],[0,0],[0,0],[0,0]],"v":[[37.15,15.273],[-0.595,10.195],[-37.149,13.648],[-37.15,18.055],[37.15,18.055]],"c":true}]},{"t":72.0000029326201,"s":[{"i":[[0,0],[14.573,0],[9.134,-8.411],[0,0],[0,0]],"o":[[-9.335,-9.76],[-13.395,0],[0,0],[0,0],[0,0]],"v":[[37.15,-2.227],[-1.096,-18.055],[-37.15,-3.852],[-37.15,18.055],[37.15,18.055]],"c":true}]}],"ix":2},"nm":"Path 1","mn":"ADBE Vector Shape - Group","hd":false},{"ty":"mm","mm":4,"nm":"Merge Paths 1","mn":"ADBE Vector Filter - Merge","hd":false},{"ty":"fl","c":{"a":0,"k":[0.16470588235294117,0.2627450980392157,0.4627450980392157,1],"ix":4},"o":{"a":0,"k":100,"ix":5},"r":1,"bm":0,"nm":"Fill 1","mn":"ADBE Vector Graphic - Fill","hd":false},{"ty":"tr","p":{"a":0,"k":[42.149,68.71],"ix":2},"a":{"a":0,"k":[0,0],"ix":1},"s":{"a":0,"k":[100,100],"ix":3},"r":{"a":0,"k":0,"ix":6},"o":{"a":1,"k":[{"i":{"x":[0.833],"y":[0.833]},"o":{"x":[0.167],"y":[0.167]},"t":64,"s":[0]},{"t":66.0000026882351,"s":[100]}],"ix":7},"sk":{"a":0,"k":0,"ix":4},"sa":{"a":0,"k":0,"ix":5},"nm":"Transform"}],"nm":"Group 2","np":3,"cix":2,"bm":0,"ix":2,"mn":"ADBE Vector Group","hd":false},{"ty":"gr","it":[{"ind":0,"ty":"sh","ix":1,"ks":{"a":0,"k":{"i":[[1.567,0],[0,0],[0,1.566],[0,0],[-1.566,0],[0,0],[0,-1.567],[0,0]],"o":[[0,0],[-1.566,0],[0,0],[0,-1.567],[0,0],[1.567,0],[0,0],[0,1.566]],"v":[[34.313,40.882],[-34.312,40.882],[-37.149,38.046],[-37.149,-38.045],[-34.312,-40.882],[34.313,-40.882],[37.149,-38.045],[37.149,38.046]],"c":true},"ix":2},"nm":"Path 1","mn":"ADBE Vector Shape - Group","hd":false},{"ty":"tm","s":{"a":0,"k":0,"ix":1},"e":{"a":1,"k":[{"i":{"x":[0.024],"y":[1]},"o":{"x":[0.333],"y":[0]},"t":64,"s":[0]},{"t":71.0000028918893,"s":[100]}],"ix":2},"o":{"a":0,"k":0,"ix":3},"m":1,"ix":2,"nm":"Trim Paths 1","mn":"ADBE Vector Filter - Trim","hd":false},{"ty":"st","c":{"a":0,"k":[0.16470588235294117,0.2627450980392157,0.4627450980392157,1],"ix":3},"o":{"a":0,"k":100,"ix":4},"w":{"a":0,"k":2,"ix":5},"lc":1,"lj":1,"ml":10,"bm":0,"nm":"Stroke 1","mn":"ADBE Vector Graphic - Stroke","hd":false},{"ty":"tr","p":{"a":0,"k":[42.149,45.883],"ix":2},"a":{"a":0,"k":[0,0],"ix":1},"s":{"a":0,"k":[100,100],"ix":3},"r":{"a":0,"k":0,"ix":6},"o":{"a":0,"k":100,"ix":7},"sk":{"a":0,"k":0,"ix":4},"sa":{"a":0,"k":0,"ix":5},"nm":"Transform"}],"nm":"Group 3","np":3,"cix":2,"bm":0,"ix":3,"mn":"ADBE Vector Group","hd":false}],"ip":64.0000026067734,"op":4560.00018573261,"st":64.0000026067734,"bm":0},{"ddd":0,"ind":12,"ty":4,"nm":"Layer 20 Outlines 4","sr":1,"ks":{"o":{"a":0,"k":100,"ix":11},"r":{"a":0,"k":0,"ix":10},"p":{"a":0,"k":[1511.276,173.891,0],"ix":2},"a":{"a":0,"k":[42.149,45.882,0],"ix":1},"s":{"a":0,"k":[100,100,100],"ix":6}},"ao":0,"shapes":[{"ty":"gr","it":[{"ind":0,"ty":"sh","ix":1,"ks":{"a":0,"k":{"i":[[0,-9.518],[9.518,0],[0,9.518],[-9.518,0]],"o":[[0,9.518],[-9.518,0],[0,-9.518],[9.518,0]],"v":[[17.235,0],[0.001,17.234],[-17.235,0],[0.001,-17.234]],"c":true},"ix":2},"nm":"Path 1","mn":"ADBE Vector Shape - Group","hd":false},{"ty":"mm","mm":4,"nm":"Merge Paths 1","mn":"ADBE Vector Filter - Merge","hd":false},{"ty":"fl","c":{"a":0,"k":[0.16470588235294117,0.2627450980392157,0.4627450980392157,1],"ix":4},"o":{"a":0,"k":100,"ix":5},"r":1,"bm":0,"nm":"Fill 1","mn":"ADBE Vector Graphic - Fill","hd":false},{"ty":"tr","p":{"a":0,"k":[41.054,30.915],"ix":2},"a":{"a":0,"k":[0,0],"ix":1},"s":{"a":1,"k":[{"i":{"x":[0.204,0.204],"y":[1,1]},"o":{"x":[0.333,0.333],"y":[0,0]},"t":57,"s":[0,0]},{"t":64.0000026067734,"s":[100,100]}],"ix":3},"r":{"a":0,"k":0,"ix":6},"o":{"a":0,"k":100,"ix":7},"sk":{"a":0,"k":0,"ix":4},"sa":{"a":0,"k":0,"ix":5},"nm":"Transform"}],"nm":"Group 1","np":3,"cix":2,"bm":0,"ix":1,"mn":"ADBE Vector Group","hd":false},{"ty":"gr","it":[{"ind":0,"ty":"sh","ix":1,"ks":{"a":1,"k":[{"i":{"x":0.833,"y":1},"o":{"x":0.167,"y":0},"t":57,"s":[{"i":[[0,0],[14.573,0],[10.873,2.507],[0,0],[0,0]],"o":[[-13.801,2.007],[-13.395,0],[0,0],[0,0],[0,0]],"v":[[37.15,15.273],[-1.595,17.258],[-37.149,13.648],[-37.15,18.055],[37.15,18.055]],"c":true}]},{"i":{"x":0,"y":1},"o":{"x":0.333,"y":0},"t":59,"s":[{"i":[[0,0],[14.573,0],[9.134,-8.411],[0,0],[0,0]],"o":[[-9.335,-9.76],[-13.395,0],[0,0],[0,0],[0,0]],"v":[[37.15,15.273],[-0.595,10.195],[-37.149,13.648],[-37.15,18.055],[37.15,18.055]],"c":true}]},{"t":65.0000026475043,"s":[{"i":[[0,0],[14.573,0],[9.134,-8.411],[0,0],[0,0]],"o":[[-9.335,-9.76],[-13.395,0],[0,0],[0,0],[0,0]],"v":[[37.15,-2.227],[-1.096,-18.055],[-37.15,-3.852],[-37.15,18.055],[37.15,18.055]],"c":true}]}],"ix":2},"nm":"Path 1","mn":"ADBE Vector Shape - Group","hd":false},{"ty":"mm","mm":4,"nm":"Merge Paths 1","mn":"ADBE Vector Filter - Merge","hd":false},{"ty":"fl","c":{"a":0,"k":[0.16470588235294117,0.2627450980392157,0.4627450980392157,1],"ix":4},"o":{"a":0,"k":100,"ix":5},"r":1,"bm":0,"nm":"Fill 1","mn":"ADBE Vector Graphic - Fill","hd":false},{"ty":"tr","p":{"a":0,"k":[42.149,68.71],"ix":2},"a":{"a":0,"k":[0,0],"ix":1},"s":{"a":0,"k":[100,100],"ix":3},"r":{"a":0,"k":0,"ix":6},"o":{"a":1,"k":[{"i":{"x":[0.833],"y":[0.833]},"o":{"x":[0.167],"y":[0.167]},"t":57,"s":[0]},{"t":59.0000024031193,"s":[100]}],"ix":7},"sk":{"a":0,"k":0,"ix":4},"sa":{"a":0,"k":0,"ix":5},"nm":"Transform"}],"nm":"Group 2","np":3,"cix":2,"bm":0,"ix":2,"mn":"ADBE Vector Group","hd":false},{"ty":"gr","it":[{"ind":0,"ty":"sh","ix":1,"ks":{"a":0,"k":{"i":[[1.567,0],[0,0],[0,1.566],[0,0],[-1.566,0],[0,0],[0,-1.567],[0,0]],"o":[[0,0],[-1.566,0],[0,0],[0,-1.567],[0,0],[1.567,0],[0,0],[0,1.566]],"v":[[34.313,40.882],[-34.312,40.882],[-37.149,38.046],[-37.149,-38.045],[-34.312,-40.882],[34.313,-40.882],[37.149,-38.045],[37.149,38.046]],"c":true},"ix":2},"nm":"Path 1","mn":"ADBE Vector Shape - Group","hd":false},{"ty":"tm","s":{"a":0,"k":0,"ix":1},"e":{"a":1,"k":[{"i":{"x":[0.024],"y":[1]},"o":{"x":[0.333],"y":[0]},"t":57,"s":[0]},{"t":64.0000026067734,"s":[100]}],"ix":2},"o":{"a":0,"k":0,"ix":3},"m":1,"ix":2,"nm":"Trim Paths 1","mn":"ADBE Vector Filter - Trim","hd":false},{"ty":"st","c":{"a":0,"k":[0.16470588235294117,0.2627450980392157,0.4627450980392157,1],"ix":3},"o":{"a":0,"k":100,"ix":4},"w":{"a":0,"k":2,"ix":5},"lc":1,"lj":1,"ml":10,"bm":0,"nm":"Stroke 1","mn":"ADBE Vector Graphic - Stroke","hd":false},{"ty":"tr","p":{"a":0,"k":[42.149,45.883],"ix":2},"a":{"a":0,"k":[0,0],"ix":1},"s":{"a":0,"k":[100,100],"ix":3},"r":{"a":0,"k":0,"ix":6},"o":{"a":0,"k":100,"ix":7},"sk":{"a":0,"k":0,"ix":4},"sa":{"a":0,"k":0,"ix":5},"nm":"Transform"}],"nm":"Group 3","np":3,"cix":2,"bm":0,"ix":3,"mn":"ADBE Vector Group","hd":false}],"ip":57.0000023216576,"op":4553.00018544749,"st":57.0000023216576,"bm":0},{"ddd":0,"ind":13,"ty":4,"nm":"Layer 20 Outlines 3","sr":1,"ks":{"o":{"a":0,"k":100,"ix":11},"r":{"a":0,"k":0,"ix":10},"p":{"a":0,"k":[1411.276,173.891,0],"ix":2},"a":{"a":0,"k":[42.149,45.882,0],"ix":1},"s":{"a":0,"k":[100,100,100],"ix":6}},"ao":0,"shapes":[{"ty":"gr","it":[{"ind":0,"ty":"sh","ix":1,"ks":{"a":0,"k":{"i":[[0,-9.518],[9.518,0],[0,9.518],[-9.518,0]],"o":[[0,9.518],[-9.518,0],[0,-9.518],[9.518,0]],"v":[[17.235,0],[0.001,17.234],[-17.235,0],[0.001,-17.234]],"c":true},"ix":2},"nm":"Path 1","mn":"ADBE Vector Shape - Group","hd":false},{"ty":"mm","mm":4,"nm":"Merge Paths 1","mn":"ADBE Vector Filter - Merge","hd":false},{"ty":"fl","c":{"a":0,"k":[0.16470588235294117,0.2627450980392157,0.4627450980392157,1],"ix":4},"o":{"a":0,"k":100,"ix":5},"r":1,"bm":0,"nm":"Fill 1","mn":"ADBE Vector Graphic - Fill","hd":false},{"ty":"tr","p":{"a":0,"k":[41.054,30.915],"ix":2},"a":{"a":0,"k":[0,0],"ix":1},"s":{"a":1,"k":[{"i":{"x":[0.204,0.204],"y":[1,1]},"o":{"x":[0.333,0.333],"y":[0,0]},"t":50,"s":[0,0]},{"t":57.0000023216576,"s":[100,100]}],"ix":3},"r":{"a":0,"k":0,"ix":6},"o":{"a":0,"k":100,"ix":7},"sk":{"a":0,"k":0,"ix":4},"sa":{"a":0,"k":0,"ix":5},"nm":"Transform"}],"nm":"Group 1","np":3,"cix":2,"bm":0,"ix":1,"mn":"ADBE Vector Group","hd":false},{"ty":"gr","it":[{"ind":0,"ty":"sh","ix":1,"ks":{"a":1,"k":[{"i":{"x":0.833,"y":1},"o":{"x":0.167,"y":0},"t":50,"s":[{"i":[[0,0],[14.573,0],[10.873,2.507],[0,0],[0,0]],"o":[[-13.801,2.007],[-13.395,0],[0,0],[0,0],[0,0]],"v":[[37.15,15.273],[-1.595,17.258],[-37.149,13.648],[-37.15,18.055],[37.15,18.055]],"c":true}]},{"i":{"x":0,"y":1},"o":{"x":0.333,"y":0},"t":52,"s":[{"i":[[0,0],[14.573,0],[9.134,-8.411],[0,0],[0,0]],"o":[[-9.335,-9.76],[-13.395,0],[0,0],[0,0],[0,0]],"v":[[37.15,15.273],[-0.595,10.195],[-37.149,13.648],[-37.15,18.055],[37.15,18.055]],"c":true}]},{"t":58.0000023623884,"s":[{"i":[[0,0],[14.573,0],[9.134,-8.411],[0,0],[0,0]],"o":[[-9.335,-9.76],[-13.395,0],[0,0],[0,0],[0,0]],"v":[[37.15,-2.227],[-1.096,-18.055],[-37.15,-3.852],[-37.15,18.055],[37.15,18.055]],"c":true}]}],"ix":2},"nm":"Path 1","mn":"ADBE Vector Shape - Group","hd":false},{"ty":"mm","mm":4,"nm":"Merge Paths 1","mn":"ADBE Vector Filter - Merge","hd":false},{"ty":"fl","c":{"a":0,"k":[0.16470588235294117,0.2627450980392157,0.4627450980392157,1],"ix":4},"o":{"a":0,"k":100,"ix":5},"r":1,"bm":0,"nm":"Fill 1","mn":"ADBE Vector Graphic - Fill","hd":false},{"ty":"tr","p":{"a":0,"k":[42.149,68.71],"ix":2},"a":{"a":0,"k":[0,0],"ix":1},"s":{"a":0,"k":[100,100],"ix":3},"r":{"a":0,"k":0,"ix":6},"o":{"a":1,"k":[{"i":{"x":[0.833],"y":[0.833]},"o":{"x":[0.167],"y":[0.167]},"t":50,"s":[0]},{"t":52.0000021180034,"s":[100]}],"ix":7},"sk":{"a":0,"k":0,"ix":4},"sa":{"a":0,"k":0,"ix":5},"nm":"Transform"}],"nm":"Group 2","np":3,"cix":2,"bm":0,"ix":2,"mn":"ADBE Vector Group","hd":false},{"ty":"gr","it":[{"ind":0,"ty":"sh","ix":1,"ks":{"a":0,"k":{"i":[[1.567,0],[0,0],[0,1.566],[0,0],[-1.566,0],[0,0],[0,-1.567],[0,0]],"o":[[0,0],[-1.566,0],[0,0],[0,-1.567],[0,0],[1.567,0],[0,0],[0,1.566]],"v":[[34.313,40.882],[-34.312,40.882],[-37.149,38.046],[-37.149,-38.045],[-34.312,-40.882],[34.313,-40.882],[37.149,-38.045],[37.149,38.046]],"c":true},"ix":2},"nm":"Path 1","mn":"ADBE Vector Shape - Group","hd":false},{"ty":"tm","s":{"a":0,"k":0,"ix":1},"e":{"a":1,"k":[{"i":{"x":[0.024],"y":[1]},"o":{"x":[0.333],"y":[0]},"t":50,"s":[0]},{"t":57.0000023216576,"s":[100]}],"ix":2},"o":{"a":0,"k":0,"ix":3},"m":1,"ix":2,"nm":"Trim Paths 1","mn":"ADBE Vector Filter - Trim","hd":false},{"ty":"st","c":{"a":0,"k":[0.16470588235294117,0.2627450980392157,0.4627450980392157,1],"ix":3},"o":{"a":0,"k":100,"ix":4},"w":{"a":0,"k":2,"ix":5},"lc":1,"lj":1,"ml":10,"bm":0,"nm":"Stroke 1","mn":"ADBE Vector Graphic - Stroke","hd":false},{"ty":"tr","p":{"a":0,"k":[42.149,45.883],"ix":2},"a":{"a":0,"k":[0,0],"ix":1},"s":{"a":0,"k":[100,100],"ix":3},"r":{"a":0,"k":0,"ix":6},"o":{"a":0,"k":100,"ix":7},"sk":{"a":0,"k":0,"ix":4},"sa":{"a":0,"k":0,"ix":5},"nm":"Transform"}],"nm":"Group 3","np":3,"cix":2,"bm":0,"ix":3,"mn":"ADBE Vector Group","hd":false}],"ip":50.0000020365418,"op":4546.00018516238,"st":50.0000020365418,"bm":0},{"ddd":0,"ind":14,"ty":4,"nm":"Layer 20 Outlines 2","sr":1,"ks":{"o":{"a":0,"k":100,"ix":11},"r":{"a":0,"k":0,"ix":10},"p":{"a":0,"k":[1313.276,173.891,0],"ix":2},"a":{"a":0,"k":[42.149,45.882,0],"ix":1},"s":{"a":0,"k":[100,100,100],"ix":6}},"ao":0,"shapes":[{"ty":"gr","it":[{"ind":0,"ty":"sh","ix":1,"ks":{"a":0,"k":{"i":[[0,-9.518],[9.518,0],[0,9.518],[-9.518,0]],"o":[[0,9.518],[-9.518,0],[0,-9.518],[9.518,0]],"v":[[17.235,0],[0.001,17.234],[-17.235,0],[0.001,-17.234]],"c":true},"ix":2},"nm":"Path 1","mn":"ADBE Vector Shape - Group","hd":false},{"ty":"mm","mm":4,"nm":"Merge Paths 1","mn":"ADBE Vector Filter - Merge","hd":false},{"ty":"fl","c":{"a":0,"k":[0.16470588235294117,0.2627450980392157,0.4627450980392157,1],"ix":4},"o":{"a":0,"k":100,"ix":5},"r":1,"bm":0,"nm":"Fill 1","mn":"ADBE Vector Graphic - Fill","hd":false},{"ty":"tr","p":{"a":0,"k":[41.054,30.915],"ix":2},"a":{"a":0,"k":[0,0],"ix":1},"s":{"a":1,"k":[{"i":{"x":[0.204,0.204],"y":[1,1]},"o":{"x":[0.333,0.333],"y":[0,0]},"t":40,"s":[0,0]},{"t":47.0000019143492,"s":[100,100]}],"ix":3},"r":{"a":0,"k":0,"ix":6},"o":{"a":0,"k":100,"ix":7},"sk":{"a":0,"k":0,"ix":4},"sa":{"a":0,"k":0,"ix":5},"nm":"Transform"}],"nm":"Group 1","np":3,"cix":2,"bm":0,"ix":1,"mn":"ADBE Vector Group","hd":false},{"ty":"gr","it":[{"ind":0,"ty":"sh","ix":1,"ks":{"a":1,"k":[{"i":{"x":0.833,"y":1},"o":{"x":0.167,"y":0},"t":40,"s":[{"i":[[0,0],[14.573,0],[10.873,2.507],[0,0],[0,0]],"o":[[-13.801,2.007],[-13.395,0],[0,0],[0,0],[0,0]],"v":[[37.15,15.273],[-1.595,17.258],[-37.149,13.648],[-37.15,18.055],[37.15,18.055]],"c":true}]},{"i":{"x":0,"y":1},"o":{"x":0.333,"y":0},"t":42,"s":[{"i":[[0,0],[14.573,0],[9.134,-8.411],[0,0],[0,0]],"o":[[-9.335,-9.76],[-13.395,0],[0,0],[0,0],[0,0]],"v":[[37.15,15.273],[-0.595,10.195],[-37.149,13.648],[-37.15,18.055],[37.15,18.055]],"c":true}]},{"t":48.0000019550801,"s":[{"i":[[0,0],[14.573,0],[9.134,-8.411],[0,0],[0,0]],"o":[[-9.335,-9.76],[-13.395,0],[0,0],[0,0],[0,0]],"v":[[37.15,-2.227],[-1.096,-18.055],[-37.15,-3.852],[-37.15,18.055],[37.15,18.055]],"c":true}]}],"ix":2},"nm":"Path 1","mn":"ADBE Vector Shape - Group","hd":false},{"ty":"mm","mm":4,"nm":"Merge Paths 1","mn":"ADBE Vector Filter - Merge","hd":false},{"ty":"fl","c":{"a":0,"k":[0.16470588235294117,0.2627450980392157,0.4627450980392157,1],"ix":4},"o":{"a":0,"k":100,"ix":5},"r":1,"bm":0,"nm":"Fill 1","mn":"ADBE Vector Graphic - Fill","hd":false},{"ty":"tr","p":{"a":0,"k":[42.149,68.71],"ix":2},"a":{"a":0,"k":[0,0],"ix":1},"s":{"a":0,"k":[100,100],"ix":3},"r":{"a":0,"k":0,"ix":6},"o":{"a":1,"k":[{"i":{"x":[0.833],"y":[0.833]},"o":{"x":[0.167],"y":[0.167]},"t":40,"s":[0]},{"t":42.0000017106951,"s":[100]}],"ix":7},"sk":{"a":0,"k":0,"ix":4},"sa":{"a":0,"k":0,"ix":5},"nm":"Transform"}],"nm":"Group 2","np":3,"cix":2,"bm":0,"ix":2,"mn":"ADBE Vector Group","hd":false},{"ty":"gr","it":[{"ind":0,"ty":"sh","ix":1,"ks":{"a":0,"k":{"i":[[1.567,0],[0,0],[0,1.566],[0,0],[-1.566,0],[0,0],[0,-1.567],[0,0]],"o":[[0,0],[-1.566,0],[0,0],[0,-1.567],[0,0],[1.567,0],[0,0],[0,1.566]],"v":[[34.313,40.882],[-34.312,40.882],[-37.149,38.046],[-37.149,-38.045],[-34.312,-40.882],[34.313,-40.882],[37.149,-38.045],[37.149,38.046]],"c":true},"ix":2},"nm":"Path 1","mn":"ADBE Vector Shape - Group","hd":false},{"ty":"tm","s":{"a":0,"k":0,"ix":1},"e":{"a":1,"k":[{"i":{"x":[0.024],"y":[1]},"o":{"x":[0.333],"y":[0]},"t":40,"s":[0]},{"t":47.0000019143492,"s":[100]}],"ix":2},"o":{"a":0,"k":0,"ix":3},"m":1,"ix":2,"nm":"Trim Paths 1","mn":"ADBE Vector Filter - Trim","hd":false},{"ty":"st","c":{"a":0,"k":[0.16470588235294117,0.2627450980392157,0.4627450980392157,1],"ix":3},"o":{"a":0,"k":100,"ix":4},"w":{"a":0,"k":2,"ix":5},"lc":1,"lj":1,"ml":10,"bm":0,"nm":"Stroke 1","mn":"ADBE Vector Graphic - Stroke","hd":false},{"ty":"tr","p":{"a":0,"k":[42.149,45.883],"ix":2},"a":{"a":0,"k":[0,0],"ix":1},"s":{"a":0,"k":[100,100],"ix":3},"r":{"a":0,"k":0,"ix":6},"o":{"a":0,"k":100,"ix":7},"sk":{"a":0,"k":0,"ix":4},"sa":{"a":0,"k":0,"ix":5},"nm":"Transform"}],"nm":"Group 3","np":3,"cix":2,"bm":0,"ix":3,"mn":"ADBE Vector Group","hd":false}],"ip":40.0000016292334,"op":4536.00018475507,"st":40.0000016292334,"bm":0},{"ddd":0,"ind":15,"ty":4,"nm":"Layer 20 Outlines","sr":1,"ks":{"o":{"a":0,"k":100,"ix":11},"r":{"a":0,"k":0,"ix":10},"p":{"a":0,"k":[1213.276,173.891,0],"ix":2},"a":{"a":0,"k":[42.149,45.882,0],"ix":1},"s":{"a":0,"k":[100,100,100],"ix":6}},"ao":0,"shapes":[{"ty":"gr","it":[{"ind":0,"ty":"sh","ix":1,"ks":{"a":0,"k":{"i":[[0,-9.518],[9.518,0],[0,9.518],[-9.518,0]],"o":[[0,9.518],[-9.518,0],[0,-9.518],[9.518,0]],"v":[[17.235,0],[0.001,17.234],[-17.235,0],[0.001,-17.234]],"c":true},"ix":2},"nm":"Path 1","mn":"ADBE Vector Shape - Group","hd":false},{"ty":"mm","mm":4,"nm":"Merge Paths 1","mn":"ADBE Vector Filter - Merge","hd":false},{"ty":"fl","c":{"a":0,"k":[0.16470588235294117,0.2627450980392157,0.4627450980392157,1],"ix":4},"o":{"a":0,"k":100,"ix":5},"r":1,"bm":0,"nm":"Fill 1","mn":"ADBE Vector Graphic - Fill","hd":false},{"ty":"tr","p":{"a":0,"k":[41.054,30.915],"ix":2},"a":{"a":0,"k":[0,0],"ix":1},"s":{"a":1,"k":[{"i":{"x":[0.204,0.204],"y":[1,1]},"o":{"x":[0.333,0.333],"y":[0,0]},"t":33,"s":[0,0]},{"t":40.0000016292334,"s":[100,100]}],"ix":3},"r":{"a":0,"k":0,"ix":6},"o":{"a":0,"k":100,"ix":7},"sk":{"a":0,"k":0,"ix":4},"sa":{"a":0,"k":0,"ix":5},"nm":"Transform"}],"nm":"Group 1","np":3,"cix":2,"bm":0,"ix":1,"mn":"ADBE Vector Group","hd":false},{"ty":"gr","it":[{"ind":0,"ty":"sh","ix":1,"ks":{"a":1,"k":[{"i":{"x":0.833,"y":1},"o":{"x":0.167,"y":0},"t":33,"s":[{"i":[[0,0],[14.573,0],[10.873,2.507],[0,0],[0,0]],"o":[[-13.801,2.007],[-13.395,0],[0,0],[0,0],[0,0]],"v":[[37.15,15.273],[-1.595,17.258],[-37.149,13.648],[-37.15,18.055],[37.15,18.055]],"c":true}]},{"i":{"x":0,"y":1},"o":{"x":0.333,"y":0},"t":35,"s":[{"i":[[0,0],[14.573,0],[9.134,-8.411],[0,0],[0,0]],"o":[[-9.335,-9.76],[-13.395,0],[0,0],[0,0],[0,0]],"v":[[37.15,15.273],[-0.595,10.195],[-37.149,13.648],[-37.15,18.055],[37.15,18.055]],"c":true}]},{"t":41.0000016699642,"s":[{"i":[[0,0],[14.573,0],[9.134,-8.411],[0,0],[0,0]],"o":[[-9.335,-9.76],[-13.395,0],[0,0],[0,0],[0,0]],"v":[[37.15,-2.227],[-1.096,-18.055],[-37.15,-3.852],[-37.15,18.055],[37.15,18.055]],"c":true}]}],"ix":2},"nm":"Path 1","mn":"ADBE Vector Shape - Group","hd":false},{"ty":"mm","mm":4,"nm":"Merge Paths 1","mn":"ADBE Vector Filter - Merge","hd":false},{"ty":"fl","c":{"a":0,"k":[0.16470588235294117,0.2627450980392157,0.4627450980392157,1],"ix":4},"o":{"a":0,"k":100,"ix":5},"r":1,"bm":0,"nm":"Fill 1","mn":"ADBE Vector Graphic - Fill","hd":false},{"ty":"tr","p":{"a":0,"k":[42.149,68.71],"ix":2},"a":{"a":0,"k":[0,0],"ix":1},"s":{"a":0,"k":[100,100],"ix":3},"r":{"a":0,"k":0,"ix":6},"o":{"a":1,"k":[{"i":{"x":[0.833],"y":[0.833]},"o":{"x":[0.167],"y":[0.167]},"t":33,"s":[0]},{"t":35.0000014255792,"s":[100]}],"ix":7},"sk":{"a":0,"k":0,"ix":4},"sa":{"a":0,"k":0,"ix":5},"nm":"Transform"}],"nm":"Group 2","np":3,"cix":2,"bm":0,"ix":2,"mn":"ADBE Vector Group","hd":false},{"ty":"gr","it":[{"ind":0,"ty":"sh","ix":1,"ks":{"a":0,"k":{"i":[[1.567,0],[0,0],[0,1.566],[0,0],[-1.566,0],[0,0],[0,-1.567],[0,0]],"o":[[0,0],[-1.566,0],[0,0],[0,-1.567],[0,0],[1.567,0],[0,0],[0,1.566]],"v":[[34.313,40.882],[-34.312,40.882],[-37.149,38.046],[-37.149,-38.045],[-34.312,-40.882],[34.313,-40.882],[37.149,-38.045],[37.149,38.046]],"c":true},"ix":2},"nm":"Path 1","mn":"ADBE Vector Shape - Group","hd":false},{"ty":"tm","s":{"a":0,"k":0,"ix":1},"e":{"a":1,"k":[{"i":{"x":[0.024],"y":[1]},"o":{"x":[0.333],"y":[0]},"t":33,"s":[0]},{"t":40.0000016292334,"s":[100]}],"ix":2},"o":{"a":0,"k":0,"ix":3},"m":1,"ix":2,"nm":"Trim Paths 1","mn":"ADBE Vector Filter - Trim","hd":false},{"ty":"st","c":{"a":0,"k":[0.16470588235294117,0.2627450980392157,0.4627450980392157,1],"ix":3},"o":{"a":0,"k":100,"ix":4},"w":{"a":0,"k":2,"ix":5},"lc":1,"lj":1,"ml":10,"bm":0,"nm":"Stroke 1","mn":"ADBE Vector Graphic - Stroke","hd":false},{"ty":"tr","p":{"a":0,"k":[42.149,45.883],"ix":2},"a":{"a":0,"k":[0,0],"ix":1},"s":{"a":0,"k":[100,100],"ix":3},"r":{"a":0,"k":0,"ix":6},"o":{"a":0,"k":100,"ix":7},"sk":{"a":0,"k":0,"ix":4},"sa":{"a":0,"k":0,"ix":5},"nm":"Transform"}],"nm":"Group 3","np":3,"cix":2,"bm":0,"ix":3,"mn":"ADBE Vector Group","hd":false}],"ip":33.0000013441176,"op":4529.00018446995,"st":33.0000013441176,"bm":0}]}],"layers":[{"ddd":0,"ind":1,"ty":0,"nm":"avtar","refId":"comp_0","sr":0.5,"ks":{"o":{"a":0,"k":100,"ix":11},"r":{"a":0,"k":0,"ix":10},"p":{"a":0,"k":[134.5,542,0],"ix":2},"a":{"a":0,"k":[960,540,0],"ix":1},"s":{"a":0,"k":[100,100,100],"ix":6}},"ao":0,"w":1920,"h":1080,"ip":0,"op":2248.00009156292,"st":0,"bm":0},{"ddd":0,"ind":2,"ty":4,"nm":"Layer 37 Outlines","sr":1,"ks":{"o":{"a":0,"k":100,"ix":11},"r":{"a":0,"k":0,"ix":10},"p":{"a":0,"k":[200.65399999999997,387.762,0],"ix":2},"a":{"a":0,"k":[-71.393,326.281,0],"ix":1},"s":{"a":1,"k":[{"i":{"x":[0.078,0.078,0.667],"y":[1,1,1]},"o":{"x":[0.333,0.333,0.333],"y":[0,0,0]},"t":0,"s":[0,0,100]},{"t":24.00000097754,"s":[100,100,100]}],"ix":6}},"ao":0,"shapes":[{"ty":"gr","it":[{"ind":0,"ty":"sh","ix":1,"ks":{"a":0,"k":{"i":[[0,-4.695],[4.694,0],[0,4.694],[-4.694,0]],"o":[[0,4.694],[-4.694,0],[0,-4.695],[4.694,0]],"v":[[8.5,0],[0,8.5],[-8.5,0],[0,-8.5]],"c":true},"ix":2},"nm":"Path 1","mn":"ADBE Vector Shape - Group","hd":false},{"ty":"mm","mm":4,"nm":"Merge Paths 1","mn":"ADBE Vector Filter - Merge","hd":false},{"ty":"fl","c":{"a":0,"k":[1,1,1,1],"ix":4},"o":{"a":0,"k":100,"ix":5},"r":1,"bm":0,"nm":"Fill 1","mn":"ADBE Vector Graphic - Fill","hd":false},{"ty":"tr","p":{"a":0,"k":[597.454,25.76],"ix":2},"a":{"a":0,"k":[0,0],"ix":1},"s":{"a":0,"k":[100,100],"ix":3},"r":{"a":0,"k":0,"ix":6},"o":{"a":0,"k":100,"ix":7},"sk":{"a":0,"k":0,"ix":4},"sa":{"a":0,"k":0,"ix":5},"nm":"Transform"}],"nm":"Group 1","np":3,"cix":2,"bm":0,"ix":1,"mn":"ADBE Vector Group","hd":false},{"ty":"gr","it":[{"ind":0,"ty":"sh","ix":1,"ks":{"a":0,"k":{"i":[[0,-4.695],[4.694,0],[0,4.694],[-4.694,0]],"o":[[0,4.694],[-4.694,0],[0,-4.695],[4.694,0]],"v":[[8.5,0],[0,8.5],[-8.5,0],[0,-8.5]],"c":true},"ix":2},"nm":"Path 1","mn":"ADBE Vector Shape - Group","hd":false},{"ty":"mm","mm":4,"nm":"Merge Paths 1","mn":"ADBE Vector Filter - Merge","hd":false},{"ty":"fl","c":{"a":0,"k":[1,1,1,1],"ix":4},"o":{"a":0,"k":100,"ix":5},"r":1,"bm":0,"nm":"Fill 1","mn":"ADBE Vector Graphic - Fill","hd":false},{"ty":"tr","p":{"a":0,"k":[569.954,25.76],"ix":2},"a":{"a":0,"k":[0,0],"ix":1},"s":{"a":0,"k":[100,100],"ix":3},"r":{"a":0,"k":0,"ix":6},"o":{"a":0,"k":100,"ix":7},"sk":{"a":0,"k":0,"ix":4},"sa":{"a":0,"k":0,"ix":5},"nm":"Transform"}],"nm":"Group 2","np":3,"cix":2,"bm":0,"ix":2,"mn":"ADBE Vector Group","hd":false},{"ty":"gr","it":[{"ind":0,"ty":"sh","ix":1,"ks":{"a":0,"k":{"i":[[0,-4.695],[4.694,0],[0,4.694],[-4.694,0]],"o":[[0,4.694],[-4.694,0],[0,-4.695],[4.694,0]],"v":[[8.5,0],[0,8.5],[-8.5,0],[0,-8.5]],"c":true},"ix":2},"nm":"Path 1","mn":"ADBE Vector Shape - Group","hd":false},{"ty":"mm","mm":4,"nm":"Merge Paths 1","mn":"ADBE Vector Filter - Merge","hd":false},{"ty":"fl","c":{"a":0,"k":[1,1,1,1],"ix":4},"o":{"a":0,"k":100,"ix":5},"r":1,"bm":0,"nm":"Fill 1","mn":"ADBE Vector Graphic - Fill","hd":false},{"ty":"tr","p":{"a":0,"k":[539.954,25.76],"ix":2},"a":{"a":0,"k":[0,0],"ix":1},"s":{"a":0,"k":[100,100],"ix":3},"r":{"a":0,"k":0,"ix":6},"o":{"a":0,"k":100,"ix":7},"sk":{"a":0,"k":0,"ix":4},"sa":{"a":0,"k":0,"ix":5},"nm":"Transform"}],"nm":"Group 3","np":3,"cix":2,"bm":0,"ix":3,"mn":"ADBE Vector Group","hd":false},{"ty":"gr","it":[{"ind":0,"ty":"sh","ix":1,"ks":{"a":0,"k":{"i":[[0,0],[0,0],[0,0],[-11.005,0],[0,0],[0,-11.005]],"o":[[0,0],[0,0],[0,-11.005],[0,0],[11.005,0],[0,0]],"v":[[309.608,20.759],[-309.608,20.759],[-309.608,-0.833],[-289.681,-20.759],[289.682,-20.759],[309.608,-0.833]],"c":true},"ix":2},"nm":"Path 1","mn":"ADBE Vector Shape - Group","hd":false},{"ty":"mm","mm":4,"nm":"Merge Paths 1","mn":"ADBE Vector Filter - Merge","hd":false},{"ty":"fl","c":{"a":0,"k":[0.16470588235294117,0.2627450980392157,0.4627450980392157,1],"ix":4},"o":{"a":0,"k":100,"ix":5},"r":1,"bm":0,"nm":"Fill 1","mn":"ADBE Vector Graphic - Fill","hd":false},{"ty":"tr","p":{"a":0,"k":[314.607,25.76],"ix":2},"a":{"a":0,"k":[0,0],"ix":1},"s":{"a":0,"k":[100,100],"ix":3},"r":{"a":0,"k":0,"ix":6},"o":{"a":0,"k":100,"ix":7},"sk":{"a":0,"k":0,"ix":4},"sa":{"a":0,"k":0,"ix":5},"nm":"Transform"}],"nm":"Group 4","np":3,"cix":2,"bm":0,"ix":4,"mn":"ADBE Vector Group","hd":false},{"ty":"gr","it":[{"ind":0,"ty":"sh","ix":1,"ks":{"a":0,"k":{"i":[[10.229,0],[0,0],[0,10.229],[0,0],[-10.228,0],[0,0],[0,-10.229],[0,0]],"o":[[0,0],[-10.228,0],[0,0],[0,-10.229],[0,0],[10.229,0],[0,0],[0,10.229]],"v":[[291.087,203.281],[-291.088,203.281],[-309.607,184.76],[-309.607,-184.759],[-291.088,-203.28],[291.087,-203.28],[309.608,-184.759],[309.608,184.76]],"c":true},"ix":2},"nm":"Path 1","mn":"ADBE Vector Shape - Group","hd":false},{"ty":"st","c":{"a":0,"k":[0.16470588235294117,0.2627450980392157,0.4627450980392157,1],"ix":3},"o":{"a":0,"k":100,"ix":4},"w":{"a":0,"k":2,"ix":5},"lc":1,"lj":1,"ml":10,"bm":0,"nm":"Stroke 1","mn":"ADBE Vector Graphic - Stroke","hd":false},{"ty":"tr","p":{"a":0,"k":[314.607,208.28],"ix":2},"a":{"a":0,"k":[0,0],"ix":1},"s":{"a":0,"k":[100,100],"ix":3},"r":{"a":0,"k":0,"ix":6},"o":{"a":0,"k":100,"ix":7},"sk":{"a":0,"k":0,"ix":4},"sa":{"a":0,"k":0,"ix":5},"nm":"Transform"}],"nm":"Group 5","np":2,"cix":2,"bm":0,"ix":5,"mn":"ADBE Vector Group","hd":false},{"ty":"gr","it":[{"ind":0,"ty":"sh","ix":1,"ks":{"a":0,"k":{"i":[[10.229,0],[0,0],[0,10.229],[0,0],[-10.228,0],[0,0],[0,-10.229],[0,0]],"o":[[0,0],[-10.228,0],[0,0],[0,-10.229],[0,0],[10.229,0],[0,0],[0,10.229]],"v":[[291.087,203.281],[-291.088,203.281],[-309.607,184.76],[-309.607,-184.759],[-291.088,-203.28],[291.087,-203.28],[309.608,-184.759],[309.608,184.76]],"c":true},"ix":2},"nm":"Path 1","mn":"ADBE Vector Shape - Group","hd":false},{"ty":"mm","mm":4,"nm":"Merge Paths 1","mn":"ADBE Vector Filter - Merge","hd":false},{"ty":"fl","c":{"a":0,"k":[1,1,1,1],"ix":4},"o":{"a":0,"k":100,"ix":5},"r":1,"bm":0,"nm":"Fill 1","mn":"ADBE Vector Graphic - Fill","hd":false},{"ty":"tr","p":{"a":0,"k":[314.607,208.28],"ix":2},"a":{"a":0,"k":[0,0],"ix":1},"s":{"a":0,"k":[100,100],"ix":3},"r":{"a":0,"k":0,"ix":6},"o":{"a":0,"k":100,"ix":7},"sk":{"a":0,"k":0,"ix":4},"sa":{"a":0,"k":0,"ix":5},"nm":"Transform"}],"nm":"Group 6","np":3,"cix":2,"bm":0,"ix":6,"mn":"ADBE Vector Group","hd":false}],"ip":0,"op":4496.00018312583,"st":0,"bm":0}],"markers":[]}